Workbook

Sheet TARIFAS CRM
A1: COMERCIALIZADORA | B1: TIPO | C1: ENERGIA | D1: TARIFA | E1: PEAJE | F1: POTENCIA 1 | G1: POTENCIA 2 | H1: POTENCIA 3 | I1: POTENCIA 4 | J1: POTENCIA 5 | K1: POTENCIA 6 | L1: T. FIJO GAS | M1: ENERGIA 1 | N1: ENERGIA 2 | O1: ENERGIA 3 | P1: ENERGIA 4 | Q1: ENERGIA 5 | R1: ENERGIA 6 | S1: T. VARIABLE GAS | T1: DESCUENTO | U1: OBJERVACIONES DESCUENTOS | V1: COMISION | W1: PERMANENCIA | X1: EXCEDENTES | Y1: BATERIA VIRTUAL | Z1: FECHA CARGA
A2: NATURGY | B2: RESIDENCIAL | C2: LUZ | D2: POR USO LUZ | E2: 2.0 | F2: 0.110283 | G2: 0.033469 | M2: 0.120471 | N2: 0.120471 | O2: 0.120471 | V2: 70 | W2: 0 | X2: 0.07 | Y2: SI | Z2: SELLO DE FECHA Y HORA
A3: NATURGY | B3: RESIDENCIAL | C3: LUZ | D3: NOCHE | E3: 2.0 | F3: 0.110283 | G3: 0.033469 | M3: 0.190465 | N3: 0.117512 | O3: 0.082673 | V3: 70 | W3: 0 | X3: 0.07 | Y3: SI | Z3: SELLO DE FECHA Y HORA
A4: NATURGY | B4: PYMES | C4: LUZ | D4: PLAN FIJO ONE TRIHORARIO | E4: 2.0 | F4: =+'Naturgy Pymes'!F17 -> 0.12297298 | G4: =+'Naturgy Pymes'!G17 -> 0.043976022 | M4: =+'Naturgy Pymes'!S17 -> 0.190964 | N4: =+'Naturgy Pymes'!T17 -> 0.117811 | O4: =+'Naturgy Pymes'!U17 -> 0.082473 | V4: SEGÚN TABLA CONSUMO | W4: 12M | X4: 0.07 | Y4: SI | Z4: SELLO DE FECHA Y HORA
A5: NATURGY | B5: PYMES | C5: LUZ | D5: PLAN FIJO TRIHORARIO | E5: 2.0 | F5: =+'Naturgy Pymes'!F17 -> 0.12297298 | G5: =+'Naturgy Pymes'!G17 -> 0.043976022 | M5: =+'Naturgy Pymes'!L17 -> 0.206464 | N5: =+'Naturgy Pymes'!M17 -> 0.133311 | O5: =+'Naturgy Pymes'!N17 -> 0.097973 | V5: SEGÚN TABLA CONSUMO | W5: 12M | X5: 0.07 | Y5: SI | Z5: SELLO DE FECHA Y HORA
A6: NATURGY | B6: PYMES | C6: LUZ | D6: PLAN FIJO SUPRA TRIHORARIO | E6: 2.0 | F6: =+'Naturgy Pymes'!F17 -> 0.12297298 | G6: =+'Naturgy Pymes'!G17 -> 0.043976022 | M6: =+'Naturgy Pymes'!Z17 -> 0.219465 | N6: =+'Naturgy Pymes'!AA17 -> 0.146312 | O6: =+'Naturgy Pymes'!AB17 -> 0.110973 | V6: SEGÚN TABLA CONSUMO | W6: 12M | X6: 0.07 | Y6: SI | Z6: SELLO DE FECHA Y HORA
A7: NATURGY | B7: PYMES | C7: LUZ | D7: PLAN FIJO ONE | E7: 2.0 | F7: =+'Naturgy Pymes'!F10 -> 0.12297298 | G7: =+'Naturgy Pymes'!G10 -> 0.043976022 | M7: =+'Naturgy Pymes'!S10 -> 0.120671 | N7: =+'Naturgy Pymes'!S10 -> 0.120671 | O7: =+'Naturgy Pymes'!S10 -> 0.120671 | V7: SEGÚN TABLA CONSUMO | W7: 12M | X7: 0.07 | Y7: SI | Z7: SELLO DE FECHA Y HORA
A8: NATURGY | B8: PYMES | C8: LUZ | D8: PLAN FIJO | E8: 2.0 | F8: =+'Naturgy Pymes'!F10 -> 0.12297298 | G8: =+'Naturgy Pymes'!G10 -> 0.043976022 | M8: =+'Naturgy Pymes'!L10 -> 0.136171 | N8: =+'Naturgy Pymes'!L10 -> 0.136171 | O8: =+'Naturgy Pymes'!L10 -> 0.136171 | V8: SEGÚN TABLA CONSUMO | W8: 12M | X8: 0.07 | Y8: SI | Z8: SELLO DE FECHA Y HORA
A9: NATURGY | B9: PYMES | C9: LUZ | D9: PLAN FIJO SUPRA | E9: 2.0 | F9: =+'Naturgy Pymes'!F10 -> 0.12297298 | G9: =+'Naturgy Pymes'!G10 -> 0.043976022 | M9: =+'Naturgy Pymes'!Z10 -> 0.149171 | N9: =+'Naturgy Pymes'!Z10 -> 0.149171 | O9: =+'Naturgy Pymes'!Z10 -> 0.149171 | V9: SEGÚN TABLA CONSUMO | W9: 12M | X9: 0.07 | Y9: SI | Z9: SELLO DE FECHA Y HORA
A10: NATURGY | B10: PYMES | C10: LUZ | D10: PLAN FIJO ONE | E10: 3.0 | F10: =+'Naturgy Pymes'!F18 -> 0.057927649 | G10: =+'Naturgy Pymes'!G18 -> 0.031189775 | H10: =+'Naturgy Pymes'!H18 -> 0.014378597 | I10: =+'Naturgy Pymes'!I18 -> 0.012747912 | J10: =+'Naturgy Pymes'!J18 -> 0.0089877041 | K10: =+'Naturgy Pymes'!K18 -> 0.0060519452 | M10: =+'Naturgy Pymes'!S18 -> 0.183593 | N10: =+'Naturgy Pymes'!T18 -> 0.158014 | O10: =+'Naturgy Pymes'!U18 -> 0.134925 | P10: =+'Naturgy Pymes'!V18 -> 0.121236 | Q10: =+'Naturgy Pymes'!W18 -> 0.114444 | R10: =+'Naturgy Pymes'!X18 -> 0.106808 | V10: SEGÚN TABLA CONSUMO | W10: 12M | X10: 0.07 | Y10: SI | Z10: SELLO DE FECHA Y HORA
A11: NATURGY | B11: PYMES | C11: LUZ | D11: PLAN FIJO | E11: 3.0 | F11: =+'Naturgy Pymes'!F18 -> 0.057927649 | G11: =+'Naturgy Pymes'!G18 -> 0.031189775 | H11: =+'Naturgy Pymes'!H18 -> 0.014378597 | I11: =+'Naturgy Pymes'!I18 -> 0.012747912 | J11: =+'Naturgy Pymes'!J18 -> 0.0089877041 | K11: =+'Naturgy Pymes'!K18 -> 0.0060519452 | M11: =+'Naturgy Pymes'!L18 -> 0.195993 | N11: =+'Naturgy Pymes'!M18 -> 0.170414 | O11: =+'Naturgy Pymes'!N18 -> 0.147424 | P11: =+'Naturgy Pymes'!O18 -> 0.133736 | Q11: =+'Naturgy Pymes'!P18 -> 0.127043 | R11: =+'Naturgy Pymes'!Q18 -> 0.119208 | V11: SEGÚN TABLA CONSUMO | W11: 12M | X11: 0.07 | Y11: SI | Z11: SELLO DE FECHA Y HORA
A12: NATURGY | B12: PYMES | C12: LUZ | D12: PLAN FIJO SUPRA | E12: 3.0 | F12: =+'Naturgy Pymes'!F18 -> 0.057927649 | G12: =+'Naturgy Pymes'!G18 -> 0.031189775 | H12: =+'Naturgy Pymes'!H18 -> 0.014378597 | I12: =+'Naturgy Pymes'!I18 -> 0.012747912 | J12: =+'Naturgy Pymes'!J18 -> 0.0089877041 | K12: =+'Naturgy Pymes'!K18 -> 0.0060519452 | M12: =+'Naturgy Pymes'!Z18 -> 0.215493 | N12: =+'Naturgy Pymes'!AA18 -> 0.189914 | O12: =+'Naturgy Pymes'!AB18 -> 0.166925 | P12: =+'Naturgy Pymes'!AC18 -> 0.153235 | Q12: =+'Naturgy Pymes'!AD18 -> 0.146543 | R12: =+'Naturgy Pymes'!AE18 -> 0.138708 | V12: SEGÚN TABLA CONSUMO | W12: 12M | X12: 0.07 | Y12: SI | Z12: SELLO DE FECHA Y HORA
A13: NATURGY | B13: PYMES | C13: LUZ | D13: PLAN FIJO ONE | E13: 6.1 | F13: =+'Naturgy Pymes'!F19 -> 0.081083211 | G13: =+'Naturgy Pymes'!G19 -> 0.042506038 | H13: =+'Naturgy Pymes'!H19 -> 0.018635277 | I13: =+'Naturgy Pymes'!I19 -> 0.014777622 | J13: =+'Naturgy Pymes'!J19 -> 0.0058222356 | K13: =+'Naturgy Pymes'!K19 -> 0.002751189 | V13: SEGÚN TABLA CONSUMO | W13: 12M | X13: 0.07 | Y13: SI | Z13: SELLO DE FECHA Y HORA
A14: NATURGY | B14: PYMES | C14: LUZ | D14: PLAN FIJO | E14: 6.1 | F14: =+'Naturgy Pymes'!F19 -> 0.081083211 | G14: =+'Naturgy Pymes'!G19 -> 0.042506038 | H14: =+'Naturgy Pymes'!H19 -> 0.018635277 | I14: =+'Naturgy Pymes'!I19 -> 0.014777622 | J14: =+'Naturgy Pymes'!J19 -> 0.0058222356 | K14: =+'Naturgy Pymes'!K19 -> 0.002751189 | V14: SEGÚN TABLA CONSUMO | W14: 12M | X14: 0.07 | Y14: SI | Z14: SELLO DE FECHA Y HORA
A15: NATURGY | B15: PYMES | C15: LUZ | D15: PLAN FIJO SUPRA | E15: 6.1 | F15: =+'Naturgy Pymes'!F19 -> 0.081083211 | G15: =+'Naturgy Pymes'!G19 -> 0.042506038 | H15: =+'Naturgy Pymes'!H19 -> 0.018635277 | I15: =+'Naturgy Pymes'!I19 -> 0.014777622 | J15: =+'Naturgy Pymes'!J19 -> 0.0058222356 | K15: =+'Naturgy Pymes'!K19 -> 0.002751189 | V15: SEGÚN TABLA CONSUMO | W15: 12M | X15: 0.07 | Y15: SI | Z15: SELLO DE FECHA Y HORA
A16: NATURGY | B16: RESIDENCIAL | C16: GAS | D16: POR USO GAS | E16: RL.1 | L16: =5.150809*0.0328767123287671 -> 0.16934167 | S16: 0.079533 | V16: 70 | W16: 0 | Z16: SELLO DE FECHA Y HORA
A17: NATURGY | B17: RESIDENCIAL | C17: GAS | D17: POR USO GAS | E17: RL.2 | L17: =9.149802*0.0328767123287671 -> 0.30081541 | S17: 0.077434 | V17: 70 | W17: 0 | Z17: SELLO DE FECHA Y HORA
A18: NATURGY | B18: RESIDENCIAL | C18: GAS | D18: POR USO GAS | E18: RL.3 | L18: =19.759738*0.0328767123287671 -> 0.64963522 | S18: 0.073993 | V18: 70 | W18: 0 | Z18: SELLO DE FECHA Y HORA
A19: NATURGY | B19: PYMES | C19: GAS | D19: PLAN COMPROMISO GAS | E19: RL.1 | L19: =+'Naturgy Pymes'!F66 -> 0.080382093 | S19: =+'Naturgy Pymes'!H66 -> 0.060064 | V19: SEGÚN TABLA CONSUMO | W19: 12M | Z19: SELLO DE FECHA Y HORA
A20: NATURGY | B20: PYMES | C20: GAS | D20: PLAN COMPROMISO GAS SUPRA | E20: RL.1 | L20: =+'Naturgy Pymes'!F66 -> 0.080382093 | S20: =+'Naturgy Pymes'!J66 -> 0.066164 | V20: SEGÚN TABLA CONSUMO | W20: 12M | Z20: SELLO DE FECHA Y HORA
A21: NATURGY | B21: PYMES | C21: GAS | D21: PLAN COMPROMISO GAS | E21: RL.2 | L21: =+'Naturgy Pymes'!F67 -> 0.21185583 | S21: =+'Naturgy Pymes'!H67 -> 0.057965 | V21: SEGÚN TABLA CONSUMO | W21: 12M | Z21: SELLO DE FECHA Y HORA
A22: NATURGY | B22: PYMES | C22: GAS | D22: PLAN COMPROMISO GAS SUPRA | E22: RL.2 | L22: =+'Naturgy Pymes'!F67 -> 0.21185583 | S22: =+'Naturgy Pymes'!J67 -> 0.064065 | V22: SEGÚN TABLA CONSUMO | W22: 12M | Z22: SELLO DE FECHA Y HORA
A23: NATURGY | B23: PYMES | C23: GAS | D23: PLAN COMPROMISO GAS | E23: RL.3 | L23: =+'Naturgy Pymes'!F68 -> 0.56067564 | S23: =+'Naturgy Pymes'!H68 -> 0.054525 | V23: SEGÚN TABLA CONSUMO | W23: 12M | Z23: SELLO DE FECHA Y HORA
A24: NATURGY | B24: PYMES | C24: GAS | D24: PLAN COMPROMISO GAS SUPRA | E24: RL.3 | L24: =+'Naturgy Pymes'!F68 -> 0.56067564 | S24: =+'Naturgy Pymes'!J68 -> 0.060625 | V24: SEGÚN TABLA CONSUMO | W24: 12M | Z24: SELLO DE FECHA Y HORA
A25: NATURGY | B25: PYMES | C25: GAS | D25: PLAN COMPROMISO GAS | E25: RL.4 | L25: =+'Naturgy Pymes'!F69 -> 1.3686556 | S25: =+'Naturgy Pymes'!H69 -> 0.058609 | V25: SEGÚN TABLA CONSUMO | W25: 12M | Z25: SELLO DE FECHA Y HORA
A26: NATURGY | B26: PYMES | C26: GAS | D26: PLAN COMPROMISO GAS SUPRA | E26: RL.4 | L26: =+'Naturgy Pymes'!F69 -> 1.3686556 | S26: =+'Naturgy Pymes'!J69 -> 0.064709 | V26: SEGÚN TABLA CONSUMO | W26: 12M | Z26: SELLO DE FECHA Y HORA
A27: NATURGY | B27: PYMES | C27: GAS | D27: PLAN COMPROMISO GAS | E27: RL.5 | L27: =+'Naturgy Pymes'!F70 -> 7.6385029 | S27: =+'Naturgy Pymes'!H70 -> 0.058546 | V27: SEGÚN TABLA CONSUMO | W27: 12M | Z27: SELLO DE FECHA Y HORA
A28: NATURGY | B28: PYMES | C28: GAS | D28: PLAN COMPROMISO GAS SUPRA | E28: RL.5 | L28: =+'Naturgy Pymes'!F69 -> 1.3686556 | S28: =+'Naturgy Pymes'!J69 -> 0.064709 | V28: SEGÚN TABLA CONSUMO | W28: 12M | Z28: SELLO DE FECHA Y HORA
A29: IBERDROLA | B29: RESIDENCIAL | C29: LUZ | D29: =+Iberdrola!B10 -> 2.0TD_2 Plan Exclusivo 15%TE/TP 1p | E29: 2.0 | F29: =+Iberdrola!U10 -> 0.11778082 | G29: =+Iberdrola!V10 -> 0.060246575 | M29: =+Iberdrola!I10 -> 0.207647 | N29: =+Iberdrola!I10 -> 0.207647 | O29: =+Iberdrola!I10 -> 0.207647 | T29: 0.15 | U29: =+Iberdrola!O10 -> 15% s/Te y Tp (+5% si PIH / PEH+ / UUEEn/ Pack Bienestar) | X29: =+Iberdrola!P10 -> 0.06 | Z29: SELLO DE FECHA Y HORA
A30: IBERDROLA | B30: RESIDENCIAL | C30: LUZ | D30: =+Iberdrola!B11 -> 2.0TD_2 Plan Exclusivo 15%TE/TP 3p | E30: 2.0 | F30: =+Iberdrola!U11 -> 0.11778082 | G30: =+Iberdrola!V11 -> 0.060246575 | M30: =+Iberdrola!I11 -> 0.2522 | N30: =+Iberdrola!I11 -> 0.2522 | O30: =+Iberdrola!I11 -> 0.2522 | T30: 0.15 | U30: =+Iberdrola!O11 -> 15% s/Te y Tp (+5% si PIH / PEH+ / UUEEn/ Pack Bienestar) | X30: =+Iberdrola!P11 -> 0.06 | Z30: SELLO DE FECHA Y HORA
A31: IBERDROLA | B31: RESIDENCIAL | C31: LUZ | D31: =+Iberdrola!B12 -> 2.0TD_2 Plan Especial plus 15%TE 1p | E31: 2.0 | F31: =+Iberdrola!U12 -> 0.10819178 | G31: =+Iberdrola!V12 -> 0.046547945 | M31: =+Iberdrola!I12 -> 0.14875 | N31: =+Iberdrola!I12 -> 0.14875 | O31: =+Iberdrola!I12 -> 0.14875 | T31: 0.15 | U31: =+Iberdrola!O12 -> 15% s/Te (+5% si PIH / PEH+ / UUEEn/ Pack Bienestar) | X31: =+Iberdrola!P12 -> 0.06 | Z31: SELLO DE FECHA Y HORA
A32: IBERDROLA | B32: RESIDENCIAL | C32: LUZ | D32: =+Iberdrola!B13 -> 2.0TD_2 Plan Hogar Especial | E32: 2.0 | F32: =+Iberdrola!U13 -> 0.084931507 | G32: =+Iberdrola!V13 -> 0.049287671 | M32: =+Iberdrola!I13 -> 0.191875 | N32: =+Iberdrola!I13 -> 0.191875 | O32: =+Iberdrola!I13 -> 0.191875 | T32: 0.15 | U32: =+Iberdrola!O13 -> 15% s/Te (+5% si PIH / PEH+ / UUEEn/ Pack Bienestar) | X32: =+Iberdrola!P13 -> 0.06 | Z32: SELLO DE FECHA Y HORA
A33: IBERDROLA | B33: RESIDENCIAL | C33: LUZ | D33: =+Iberdrola!B14 -> 2.0TD_2 Plan Estable | E33: 2.0 | F33: =+Iberdrola!U14 -> 0.10819178 | G33: =+Iberdrola!V14 -> 0.046547945 | M33: =+Iberdrola!I14 -> 0.174875 | N33: =+Iberdrola!I14 -> 0.174875 | O33: =+Iberdrola!I14 -> 0.174875 | T33: 0.15 | U33: =+Iberdrola!O14 -> 15% s/Te (+5% si PIH / PEH+ / UUEEn/ Pack Bienestar) | X33: =+Iberdrola!P14 -> 0.06 | Z33: SELLO DE FECHA Y HORA
A34: IBERDROLA | B34: RESIDENCIAL | C34: LUZ | D34: =+Iberdrola!B15 -> 2.0TD_2 Planazo | E34: 2.0 | F34: =+Iberdrola!U15 -> 0.10819178 | G34: =+Iberdrola!V15 -> 0.049287671 | M34: =+Iberdrola!I15 -> 0.191875 | N34: =+Iberdrola!I15 -> 0.191875 | O34: =+Iberdrola!I15 -> 0.191875 | T34: 0.15 | U34: =+Iberdrola!O15 -> 15% s/Te (+5% si PIH / PEH+ / UUEEn/ Pack Bienestar) + 100€ en conciertos | X34: =+Iberdrola!P15 -> 0.06 | Z34: SELLO DE FECHA Y HORA
A35: IBERDROLA | B35: RESIDENCIAL | C35: LUZ | D35: =+Iberdrola!B16 -> 2.0TD_2 Plan Más Ahorro | E35: 2.0 | F35: =+Iberdrola!U16 -> 0.10819178 | G35: =+Iberdrola!V16 -> 0.049287671 | M35: =+Iberdrola!I16 -> 0.171111 | N35: =+Iberdrola!I16 -> 0.171111 | O35: =+Iberdrola!I16 -> 0.171111 | T35: 0.1 | U35: =+Iberdrola!O16 -> 10% / 15% / 20% /25% / 30% Te (+5% si PIH / PEH+ / UUEEn/ Pack Bienestar) | X35: =+Iberdrola!P16 -> 0.06 | Z35: SELLO DE FECHA Y HORA
A36: IBERDROLA | B36: RESIDENCIAL | C36: LUZ | D36: =+Iberdrola!B17 -> 2.0TD_2 Plan Ahorro Inteligente 8 horas | E36: 2.0 | F36: =+Iberdrola!U17 -> 0.10819178 | G36: =+Iberdrola!V17 -> 0.049287671 | M36: =+Iberdrola!I17 -> 0.23526 | N36: =+Iberdrola!I17 -> 0.23526 | O36: =+Iberdrola!I17 -> 0.23526 | T36: 0.15 | U36: =+Iberdrola!O17 -> 15% s/Te (+5% si PIH / PEH+) | X36: =+Iberdrola!P17 -> 0.06 | Z36: SELLO DE FECHA Y HORA
A37: IBERDROLA | B37: RESIDENCIAL | C37: LUZ | D37: =+Iberdrola!B18 -> 2.0TD_2 Plan Ahorro Automático 100 | E37: 2.0 | F37: =+Iberdrola!U18 -> 0.10819178 | G37: =+Iberdrola!V18 -> 0.049287671 | M37: =+Iberdrola!I18 -> 0.217 | N37: =+Iberdrola!I18 -> 0.217 | O37: =+Iberdrola!I18 -> 0.217 | U37: =+Iberdrola!O18 -> 100€ (+20€ si PIH / PEH+/ PI / PEH ); 50% dos días de más consumo | X37: =+Iberdrola!P18 -> 0.06 | Z37: SELLO DE FECHA Y HORA
A38: IBERDROLA | B38: RESIDENCIAL | C38: LUZ | D38: =+Iberdrola!B19 -> 2.0TD_2 Plan Verano | E38: 2.0 | F38: =+Iberdrola!U19 -> 0.10819178 | G38: =+Iberdrola!V19 -> 0.049287671 | M38: =+Iberdrola!I19 -> 0.249822 | N38: =+Iberdrola!I19 -> 0.249822 | O38: =+Iberdrola!I19 -> 0.249822 | T38: 0.15 | U38: =+Iberdrola!O19 -> 15% s/Tp (+5% si PIH / PEH+ / UUEEn/ Pack Bienestar) | X38: =+Iberdrola!P19 -> 0.06 | Z38: SELLO DE FECHA Y HORA
A39: IBERDROLA | B39: RESIDENCIAL | C39: LUZ | D39: =+Iberdrola!B20 -> 2.0TD_2 Plan Estable Comunidades de Propietarios | E39: 2.0 | F39: =+Iberdrola!U20 -> 0.11641096 | G39: =+Iberdrola!V20 -> 0.052027397 | M39: =+Iberdrola!I20 -> 0.159131 | N39: =+Iberdrola!I20 -> 0.159131 | O39: =+Iberdrola!I20 -> 0.159131 | T39: 0.15 | U39: =+Iberdrola!O20 -> 15% s/Te (+5% si ACP) + 5% s/te 2año | X39: =+Iberdrola!P20 -> 0.06 | Z39: SELLO DE FECHA Y HORA
A40: IBERDROLA | B40: RESIDENCIAL | C40: LUZ | D40: =+Iberdrola!B21 -> 2.0TD_2 Plan Solar | E40: 2.0 | F40: =+Iberdrola!U21 -> 0.10819178 | G40: =+Iberdrola!V21 -> 0.049287671 | M40: =+Iberdrola!I21 -> 0.244 | N40: =+Iberdrola!I21 -> 0.244 | O40: =+Iberdrola!I21 -> 0.244 | U40: =+Iberdrola!O21 -> s/ dto | X40: =+Iberdrola!P21 -> 0.06 | Z40: SELLO DE FECHA Y HORA
A41: IBERDROLA | B41: RESIDENCIAL | C41: LUZ | D41: =+Iberdrola!B22 -> 2.0TD_2 Plan Recarga Inteligente | E41: 2.0 | F41: =+Iberdrola!U22 -> 0.10819178 | G41: =+Iberdrola!V22 -> 0.049287671 | M41: =+Iberdrola!I22 -> 0.149999 | N41: =+Iberdrola!I22 -> 0.149999 | O41: =+Iberdrola!I22 -> 0.149999 | U41: =+Iberdrola!O22 -> s/ dto | X41: =+Iberdrola!P22 -> 0.06 | Z41: SELLO DE FECHA Y HORA
A42: IBERDROLA | B42: RESIDENCIAL | C42: LUZ | D42: =+Iberdrola!B23 -> 2.0TD_2 Impulsa 24h | E42: 2.0 | F42: =+Iberdrola!U23 -> 0.11641096 | G42: =+Iberdrola!V23 -> 0.046547945 | M42: =+Iberdrola!I23 -> 0.1732 | N42: =+Iberdrola!I23 -> 0.1732 | O42: =+Iberdrola!I23 -> 0.1732 | T42: 0.2 | U42: =+Iberdrola!O23 -> 20% s/Te (+5% si PIH / PEH+ / UUEEn/ Pack Bienestar) | X42: =+Iberdrola!P23 -> 0.06 | Z42: SELLO DE FECHA Y HORA
A43: IBERDROLA | B43: RESIDENCIAL | C43: LUZ | D43: =+Iberdrola!B24 -> 2.0TD_2 Plan OMIE | E43: 2.0 | F43: =+Iberdrola!U24 -> 0.073782329 | G43: =+Iberdrola!V24 -> 0.0019112 | M43: =+Iberdrola!I24 -> 0.015 | N43: =+Iberdrola!I24 -> 0.015 | O43: =+Iberdrola!I24 -> 0.015 | U43: =+Iberdrola!O24 -> s/ dto (únicamente para fidelización) | X43: =+Iberdrola!P24 -> PVPC | Z43: SELLO DE FECHA Y HORA
A44: IBERDROLA | B44: RESIDENCIAL | C44: LUZ | D44: =+Iberdrola!B25 -> 2.0TD_2 Plan OMIE Comunidades | E44: 2.0 | F44: =+Iberdrola!U25 -> 0.073782329 | G44: =+Iberdrola!V25 -> 0.0019112 | M44: =+Iberdrola!I25 -> 0.03 | N44: =+Iberdrola!I25 -> 0.03 | O44: =+Iberdrola!I25 -> 0.03 | U44: =+Iberdrola!O25 -> s/ dto | X44: =+Iberdrola!P25 -> PVPC | Z44: SELLO DE FECHA Y HORA
A45: IBERDROLA | B45: RESIDENCIAL | C45: LUZ | D45: =+Iberdrola!B27 -> 2.0TD_3 Plan Exclusivo 15%TE/TP 1p | E45: 2.0 | F45: =+Iberdrola!U27 -> 0.11778082 | G45: =+Iberdrola!V27 -> 0.060246575 | M45: =+Iberdrola!I27 -> 0.207647 | N45: =+Iberdrola!I27 -> 0.207647 | O45: =+Iberdrola!I27 -> 0.207647 | X45: =+Iberdrola!P27 -> 0.06 | Z45: SELLO DE FECHA Y HORA
A46: IBERDROLA | B46: RESIDENCIAL | C46: LUZ | D46: =+Iberdrola!B28 -> 2.0TD_3 Plan Exclusivo 15%TE/TP 3p | E46: 2.0 | F46: =+Iberdrola!U28 -> 0.11778082 | G46: =+Iberdrola!V28 -> 0.060246575 | M46: =+Iberdrola!I28 -> 0.2481 | N46: =+Iberdrola!I28 -> 0.2481 | O46: =+Iberdrola!I28 -> 0.2481 | T46: 0.15 | U46: =+Iberdrola!O27 -> 15% s/Te y Tp (+5% si PIH / PEH+ / UUEEn/ Pack Bienestar) | X46: =+Iberdrola!P28 -> 0.06 | Z46: SELLO DE FECHA Y HORA
A47: IBERDROLA | B47: RESIDENCIAL | C47: LUZ | D47: =+Iberdrola!B29 -> 2.0TD_3 Plan Especial plus 15%TE 1p | E47: 2.0 | F47: =+Iberdrola!U29 -> 0.10819178 | G47: =+Iberdrola!V29 -> 0.046547945 | M47: =+Iberdrola!I29 -> 0.15375 | N47: =+Iberdrola!I29 -> 0.15375 | O47: =+Iberdrola!I29 -> 0.15375 | T47: 0.15 | U47: =+Iberdrola!O28 -> 15% s/Te y Tp (+5% si PIH / PEH+ / UUEEn/ Pack Bienestar) | X47: =+Iberdrola!P29 -> 0.06 | Z47: SELLO DE FECHA Y HORA
A48: IBERDROLA | B48: RESIDENCIAL | C48: LUZ | D48: =+Iberdrola!B30 -> 2.0TD_3 Plan Hogar Especial | E48: 2.0 | F48: =+Iberdrola!U30 -> 0.084931507 | G48: =+Iberdrola!V30 -> 0.049287671 | M48: =+Iberdrola!I30 -> 0.196875 | N48: =+Iberdrola!I30 -> 0.196875 | O48: =+Iberdrola!I30 -> 0.196875 | T48: 0.15 | U48: =+Iberdrola!O29 -> 15% s/Te (+5% si PIH / PEH+ / UUEEn/ Pack Bienestar) | X48: =+Iberdrola!P30 -> 0.06 | Z48: SELLO DE FECHA Y HORA
A49: IBERDROLA | B49: RESIDENCIAL | C49: LUZ | D49: =+Iberdrola!B31 -> 2.0TD_3 Plan Estable | E49: 2.0 | F49: =+Iberdrola!U31 -> 0.10819178 | G49: =+Iberdrola!V31 -> 0.046547945 | M49: =+Iberdrola!I31 -> 0.174875 | N49: =+Iberdrola!I31 -> 0.174875 | O49: =+Iberdrola!I31 -> 0.174875 | T49: 0.15 | U49: =+Iberdrola!O30 -> 15% s/Te (+5% si PIH / PEH+ / UUEEn/ Pack Bienestar) | X49: =+Iberdrola!P31 -> 0.06 | Z49: SELLO DE FECHA Y HORA
A50: IBERDROLA | B50: RESIDENCIAL | C50: LUZ | D50: =+Iberdrola!B32 -> 2.0TD_3 Planazo | E50: 2.0 | F50: =+Iberdrola!U32 -> 0.10819178 | G50: =+Iberdrola!V32 -> 0.049287671 | M50: =+Iberdrola!I32 -> 0.191875 | N50: =+Iberdrola!I32 -> 0.191875 | O50: =+Iberdrola!I32 -> 0.191875 | T50: 0.15 | U50: =+Iberdrola!O31 -> 15% s/Te (+5% si PIH / PEH+ / UUEEn/ Pack Bienestar) | X50: =+Iberdrola!P32 -> 0.06 | Z50: SELLO DE FECHA Y HORA
A51: IBERDROLA | B51: RESIDENCIAL | C51: LUZ | D51: =+Iberdrola!B33 -> 2.0TD_3 Plan Más Ahorro | E51: 2.0 | F51: =+Iberdrola!U33 -> 0.10819178 | G51: =+Iberdrola!V33 -> 0.049287671 | M51: =+Iberdrola!I33 -> 0.181111 | N51: =+Iberdrola!I33 -> 0.181111 | O51: =+Iberdrola!I33 -> 0.181111 | T51: 0.15 | U51: =+Iberdrola!O32 -> 15% s/Te (+5% si PIH / PEH+ / UUEEn/ Pack Bienestar) + 100€ en conciertos | X51: =+Iberdrola!P33 -> 0.06 | Z51: SELLO DE FECHA Y HORA
A52: IBERDROLA | B52: RESIDENCIAL | C52: LUZ | D52: =+Iberdrola!B34 -> 2.0TD_3 Plan Ahorro Inteligente 8 horas | E52: 2.0 | F52: =+Iberdrola!U34 -> 0.10819178 | G52: =+Iberdrola!V34 -> 0.049287671 | M52: =+Iberdrola!I34 -> 0.24526 | N52: =+Iberdrola!I34 -> 0.24526 | O52: =+Iberdrola!I34 -> 0.24526 | T52: 0.1 | U52: =+Iberdrola!O33 -> 10% / 15% / 20% /25% / 30% Te (+5% si PIH / PEH+ / UUEEn/ Pack Bienestar) | X52: =+Iberdrola!P34 -> 0.06 | Z52: SELLO DE FECHA Y HORA
A53: IBERDROLA | B53: RESIDENCIAL | C53: LUZ | D53: =+Iberdrola!B35 -> 2.0TD_3 Plan Ahorro Automático 100 | E53: 2.0 | F53: =+Iberdrola!U35 -> 0.10819178 | G53: =+Iberdrola!V35 -> 0.049287671 | M53: =+Iberdrola!I35 -> 0.217 | N53: =+Iberdrola!I35 -> 0.217 | O53: =+Iberdrola!I35 -> 0.217 | T53: 0.15 | U53: =+Iberdrola!O34 -> 15% s/Te (+5% si PIH / PEH+ / UUEEn/ Pack Bienestar) | X53: =+Iberdrola!P35 -> 0.06 | Z53: SELLO DE FECHA Y HORA
A54: IBERDROLA | B54: RESIDENCIAL | C54: LUZ | D54: =+Iberdrola!B36 -> 2.0TD_3 Plan Verano | E54: 2.0 | F54: =+Iberdrola!U36 -> 0.10819178 | G54: =+Iberdrola!V36 -> 0.049287671 | M54: =+Iberdrola!I36 -> 0.249822 | N54: =+Iberdrola!I36 -> 0.249822 | O54: =+Iberdrola!I36 -> 0.249822 | U54: =+Iberdrola!O35 -> 100€ (+20€ si PIH / PEH+/ PI / PEH ) | X54: =+Iberdrola!P36 -> 0.06 | Z54: SELLO DE FECHA Y HORA
A55: IBERDROLA | B55: RESIDENCIAL | C55: LUZ | D55: =+Iberdrola!B37 -> 2.0TD_3 Plan Estable Comunidades de Propietarios | E55: 2.0 | F55: =+Iberdrola!U37 -> 0.11641096 | G55: =+Iberdrola!V37 -> 0.052027397 | M55: =+Iberdrola!I37 -> 0.159131 | N55: =+Iberdrola!I37 -> 0.159131 | O55: =+Iberdrola!I37 -> 0.159131 | T55: 0.15 | U55: =+Iberdrola!O36 -> 15% s/Tp (+5% si PIH / PEH+ / UUEEn/ Pack Bienestar) | X55: =+Iberdrola!P37 -> 0.06 | Z55: SELLO DE FECHA Y HORA
A56: IBERDROLA | B56: RESIDENCIAL | C56: LUZ | D56: =+Iberdrola!B38 -> 2.0TD_3 Plan Solar | E56: 2.0 | F56: =+Iberdrola!U38 -> 0.10819178 | G56: =+Iberdrola!V38 -> 0.049287671 | M56: =+Iberdrola!I38 -> 0.244 | N56: =+Iberdrola!I38 -> 0.244 | O56: =+Iberdrola!I38 -> 0.244 | T56: 0.15 | U56: =+Iberdrola!O37 -> 15% s/Te (+5% si ACP) + 5% s/te 2año | X56: =+Iberdrola!P38 -> 0.06 | Z56: SELLO DE FECHA Y HORA
A57: IBERDROLA | B57: RESIDENCIAL | C57: LUZ | D57: =+Iberdrola!B39 -> 2.0TD_3 Plan Recarga Inteligente | E57: 2.0 | F57: =+Iberdrola!U39 -> 0.10819178 | G57: =+Iberdrola!V39 -> 0.049287671 | M57: =+Iberdrola!I39 -> 0.149999 | N57: =+Iberdrola!I39 -> 0.149999 | O57: =+Iberdrola!I39 -> 0.149999 | U57: =+Iberdrola!O38 -> s/ dto | X57: =+Iberdrola!P39 -> 0.06 | Z57: SELLO DE FECHA Y HORA
A58: IBERDROLA | B58: RESIDENCIAL | C58: LUZ | D58: =+Iberdrola!B40 -> 2.0TD_3 Impulsa 24h | E58: 2.0 | F58: =+Iberdrola!U40 -> 0.11641096 | G58: =+Iberdrola!V40 -> 0.046547945 | M58: =+Iberdrola!I40 -> 0.1732 | N58: =+Iberdrola!I40 -> 0.1732 | O58: =+Iberdrola!I40 -> 0.1732 | U58: =+Iberdrola!O39 -> s/ dto | X58: =+Iberdrola!P40 -> 0.06 | Z58: SELLO DE FECHA Y HORA
A59: IBERDROLA | B59: RESIDENCIAL | C59: LUZ | D59: =+Iberdrola!B41 -> 2.0TD_3 Plan OMIE | E59: 2.0 | F59: =+Iberdrola!U41 -> 0.073782329 | G59: =+Iberdrola!V41 -> 0.0019112 | M59: =+Iberdrola!I41 -> 0.03 | N59: =+Iberdrola!I41 -> 0.03 | O59: =+Iberdrola!I41 -> 0.03 | T59: 0.2 | U59: =+Iberdrola!O40 -> 20% s/Te (+5% si PIH / PEH+ / UUEEn/ Pack Bienestar) | X59: =+Iberdrola!P41 -> PVPC | Z59: SELLO DE FECHA Y HORA
A60: IBERDROLA | B60: RESIDENCIAL | C60: LUZ | D60: =+Iberdrola!B42 -> 2.0TD_3 Plan OMIE Comunidades | E60: 2.0 | F60: =+Iberdrola!U42 -> 0.073782329 | G60: =+Iberdrola!V42 -> 0.0019112 | M60: =+Iberdrola!I42 -> 0.03 | N60: =+Iberdrola!I42 -> 0.03 | O60: =+Iberdrola!I42 -> 0.03 | U60: =+Iberdrola!O41 -> s/ dto | X60: =+Iberdrola!P42 -> PVPC | Z60: SELLO DE FECHA Y HORA
A61: IBERDROLA | B61: RESIDENCIAL | C61: LUZ | D61: =+Iberdrola!B43 -> 2.0TD Eventual/Temporal (s/IE) | E61: 2.0 | F61: =+Iberdrola!U43 -> 0.16572603 | G61: =+Iberdrola!V43 -> 0.0067945205 | M61: =+Iberdrola!I43 -> 0.2881 | N61: =+Iberdrola!I43 -> 0.2881 | O61: =+Iberdrola!I43 -> 0.2881 | U61: =+Iberdrola!O42 -> s/ dto | X61: =+Iberdrola!P43 -> 0.06 | Z61: SELLO DE FECHA Y HORA
A62: IBERDROLA | B62: PYMES | C62: LUZ | D62: =+Iberdrola!B46 -> 3.0TD Impulsa 24h | E62: 3.0 | F62: =+Iberdrola!C46/365 -> 0.059171271 | G62: =+Iberdrola!D46/365 -> 0.031974014 | H62: =+Iberdrola!E46/365 -> 0.019047397 | I62: =+Iberdrola!F46/365 -> 0.014789271 | J62: =+Iberdrola!G46/365 -> 0.0089287288 | K62: =+Iberdrola!H46/365 -> 0.0075545397 | M62: =+Iberdrola!I46 -> 0.184 | N62: =+Iberdrola!I46 -> 0.184 | O62: =+Iberdrola!I46 -> 0.184 | U62: =+Iberdrola!O45 -> 0 | X62: =+Iberdrola!P46 -> 0.03 | Z62: SELLO DE FECHA Y HORA
A63: IBERDROLA | B63: PYMES | C63: LUZ | D63: =+Iberdrola!B47 -> 3.0TD Impulsa 24h+ | E63: 3.0 | F63: =+Iberdrola!C47/365 -> 0.059171271 | G63: =+Iberdrola!D47/365 -> 0.031974014 | H63: =+Iberdrola!E47/365 -> 0.019047397 | I63: =+Iberdrola!F47/365 -> 0.014789271 | J63: =+Iberdrola!G47/365 -> 0.0089287288 | K63: =+Iberdrola!H47/365 -> 0.0075545397 | M63: =+Iberdrola!I47 -> 0.191 | N63: =+Iberdrola!I47 -> 0.191 | O63: =+Iberdrola!I47 -> 0.191 | T63: 0.2 | U63: =+Iberdrola!O46 -> 20% s/Te (+5% si UUEEn) | X63: =+Iberdrola!P47 -> 0.03 | Z63: SELLO DE FECHA Y HORA
A64: IBERDROLA | B64: PYMES | C64: LUZ | D64: =+Iberdrola!B48 -> 3.0TD Impulsa Zero+ | E64: 3.0 | F64: =+Iberdrola!C48/365 -> 0.059171271 | G64: =+Iberdrola!D48/365 -> 0.040193192 | H64: =+Iberdrola!E48/365 -> 0.030006301 | I64: =+Iberdrola!F48/365 -> 0.028487901 | J64: =+Iberdrola!G48/365 -> 0.025367085 | K64: =+Iberdrola!H48/365 -> 0.023992896 | M64: =+Iberdrola!I48 -> 0.168 | N64: =+Iberdrola!I48 -> 0.168 | O64: =+Iberdrola!I48 -> 0.168 | T64: 0.2 | U64: =+Iberdrola!O47 -> 20% s/Te 1º año y 30% s/Te 2º año (+5% si UUEEn) | X64: =+Iberdrola!P48 -> 0.03 | Z64: SELLO DE FECHA Y HORA
A65: IBERDROLA | B65: PYMES | C65: LUZ | D65: =+Iberdrola!B49 -> 3.0TD Impulsa Negocio | E65: 3.0 | F65: =+Iberdrola!C49/365 -> 0.059171271 | G65: =+Iberdrola!D49/365 -> 0.031974014 | H65: =+Iberdrola!E49/365 -> 0.019047397 | I65: =+Iberdrola!F49/365 -> 0.014789271 | J65: =+Iberdrola!G49/365 -> 0.0089287288 | K65: =+Iberdrola!H49/365 -> 0.0075545397 | M65: =+Iberdrola!I49 -> 0.269 | N65: =+Iberdrola!I49 -> 0.269 | O65: =+Iberdrola!I49 -> 0.269 | T65: 0.2 | U65: =+Iberdrola!O48 -> 20% s/Te 1º año y 10% s/Te 2º año (+5% si UUEEn) | X65: =+Iberdrola!P49 -> 0.03 | Z65: SELLO DE FECHA Y HORA
A66: IBERDROLA | B66: PYMES | C66: LUZ | D66: =+Iberdrola!B50 -> 3.0TD Impulsa Valle | E66: 3.0 | F66: =+Iberdrola!C50/365 -> 0.059171271 | G66: =+Iberdrola!D50/365 -> 0.031974014 | H66: =+Iberdrola!E50/365 -> 0.019047397 | I66: =+Iberdrola!F50/365 -> 0.014789271 | J66: =+Iberdrola!G50/365 -> 0.0089287288 | K66: =+Iberdrola!H50/365 -> 0.0075545397 | M66: =+Iberdrola!I50 -> 0.269 | N66: =+Iberdrola!I50 -> 0.269 | O66: =+Iberdrola!I50 -> 0.269 | T66: 0.2 | U66: =+Iberdrola!O49 -> 20% s/Te (+5% si UUEEn) | X66: =+Iberdrola!P50 -> 0.03 | Z66: SELLO DE FECHA Y HORA
A67: IBERDROLA | B67: PYMES | C67: LUZ | D67: =+Iberdrola!B51 -> 3.0TD Impulsa Estable | E67: 3.0 | F67: =+Iberdrola!C51/365 -> 0.023972603 | G67: =+Iberdrola!D51/365 -> 0.023972603 | H67: =+Iberdrola!E51/365 -> 0.023972603 | I67: =+Iberdrola!F51/365 -> 0.023972603 | J67: =+Iberdrola!G51/365 -> 0.023972603 | K67: =+Iberdrola!H51/365 -> 0.023972603 | M67: =+Iberdrola!I51 -> 0.199 | N67: =+Iberdrola!I51 -> 0.199 | O67: =+Iberdrola!I51 -> 0.199 | T67: 0.2 | U67: =+Iberdrola!O50 -> 20% s/Te (+5% si UUEEn) | X67: =+Iberdrola!P51 -> 0.03 | Z67: SELLO DE FECHA Y HORA
A68: IBERDROLA | B68: PYMES | C68: LUZ | D68: =+Iberdrola!B52 -> 3.0TD Comunidad Exclusivo | E68: 3.0 | F68: =+Iberdrola!C52/365 -> 0.06710037 | G68: =+Iberdrola!D52/365 -> 0.034783978 | H68: =+Iberdrola!E52/365 -> 0.026039474 | I68: =+Iberdrola!F52/365 -> 0.019272564 | J68: =+Iberdrola!G52/365 -> 0.014713468 | K68: =+Iberdrola!H52/365 -> 0.010931104 | M68: =+Iberdrola!I52 -> 0.199 | N68: =+Iberdrola!I52 -> 0.199 | O68: =+Iberdrola!I52 -> 0.199 | T68: 0.2 | U68: =+Iberdrola!O51 -> 20% s/Te y TP (+5% TE si UUEEn) | X68: =+Iberdrola!P52 -> 0.03 | Z68: SELLO DE FECHA Y HORA
A69: IBERDROLA | B69: PYMES | C69: LUZ | D69: =+Iberdrola!B53 -> 3.0TD Comunidad Impulsa | E69: 3.0 | F69: =+Iberdrola!C53/365 -> 0.059171271 | G69: =+Iberdrola!D53/365 -> 0.031974014 | H69: =+Iberdrola!E53/365 -> 0.019047397 | I69: =+Iberdrola!F53/365 -> 0.014789271 | J69: =+Iberdrola!G53/365 -> 0.0089287288 | K69: =+Iberdrola!H53/365 -> 0.0075545397 | M69: =+Iberdrola!I53 -> 0.179 | N69: =+Iberdrola!I53 -> 0.179 | O69: =+Iberdrola!I53 -> 0.179 | T69: 0.2 | U69: =+Iberdrola!O52 -> 20% s/Te (+5% si ACP) + 5% s/te 2año | X69: =+Iberdrola!P53 -> 0.03 | Z69: SELLO DE FECHA Y HORA
A70: IBERDROLA | B70: PYMES | C70: LUZ | D70: =+Iberdrola!B54 -> 3.0TD Comunidad Optima | E70: 3.0 | F70: =+Iberdrola!C54/365 -> 0.059171271 | G70: =+Iberdrola!D54/365 -> 0.031974014 | H70: =+Iberdrola!E54/365 -> 0.019047397 | I70: =+Iberdrola!F54/365 -> 0.014789271 | J70: =+Iberdrola!G54/365 -> 0.0089287288 | K70: =+Iberdrola!H54/365 -> 0.0075545397 | M70: =+Iberdrola!I54 -> 0.174 | N70: =+Iberdrola!I54 -> 0.174 | O70: =+Iberdrola!I54 -> 0.174 | T70: 0.2 | U70: =+Iberdrola!O53 -> 20% s/Te (+5% si ACP) + 5% s/te 2año | X70: =+Iberdrola!P54 -> 0.03 | Z70: SELLO DE FECHA Y HORA
A71: IBERDROLA | B71: PYMES | C71: LUZ | D71: =+Iberdrola!B55 -> 3.0TD Plan Vehículo Eléctrico | E71: 3.0 | F71: =+Iberdrola!C55/365 -> 0.062199627 | G71: =+Iberdrola!D55/365 -> 0.033076403 | H71: =+Iberdrola!E55/365 -> 0.021533203 | I71: =+Iberdrola!F55/365 -> 0.015845605 | J71: =+Iberdrola!G55/365 -> 0.0094946384 | K71: =+Iberdrola!H55/365 -> 0.0066298438 | M71: =+Iberdrola!I55 -> 0.296 | N71: =+Iberdrola!I55 -> 0.296 | O71: =+Iberdrola!I55 -> 0.296 | T71: 0.2 | U71: =+Iberdrola!O54 -> 20% s/Te (+5% si ACP) + 5% s/te 2año | X71: =+Iberdrola!P55 -> 0.03 | Z71: SELLO DE FECHA Y HORA
A72: IBERDROLA | B72: PYMES | C72: LUZ | D72: =+Iberdrola!B56 -> 3.0TD Plan Regantes | E72: 3.0 | F72: =+Iberdrola!C56/365 -> 0.062199627 | G72: =+Iberdrola!D56/365 -> 0.033076403 | H72: =+Iberdrola!E56/365 -> 0.021533203 | I72: =+Iberdrola!F56/365 -> 0.015845605 | J72: =+Iberdrola!G56/365 -> 0.0094946384 | K72: =+Iberdrola!H56/365 -> 0.0066298438 | M72: =+Iberdrola!I56 -> 0.271 | N72: =+Iberdrola!I56 -> 0.271 | O72: =+Iberdrola!I56 -> 0.271 | U72: =+Iberdrola!O55 -> s/ dto | X72: =+Iberdrola!P56 -> 0.03 | Z72: SELLO DE FECHA Y HORA
A73: IBERDROLA | B73: PYMES | C73: LUZ | D73: =+Iberdrola!B57 -> 3.0TD Plan Exclusivo 15%TE | E73: 3.0 | F73: =+Iberdrola!C57/365 -> 0.06710037 | G73: =+Iberdrola!D57/365 -> 0.034783978 | H73: =+Iberdrola!E57/365 -> 0.026039474 | I73: =+Iberdrola!F57/365 -> 0.019272564 | J73: =+Iberdrola!G57/365 -> 0.014713468 | K73: =+Iberdrola!H57/365 -> 0.010931104 | M73: =+Iberdrola!I57 -> 0.284832 | N73: =+Iberdrola!I57 -> 0.284832 | O73: =+Iberdrola!I57 -> 0.284832 | P73: =+Iberdrola!J57 -> 0.255068 | Q73: =+Iberdrola!K57 -> 0.227022 | R73: =+Iberdrola!L57 -> 0.210872 | U73: =+Iberdrola!O56 -> s/ dto | X73: =+Iberdrola!P57 -> 0.05 | Z73: SELLO DE FECHA Y HORA
A74: IBERDROLA | B74: PYMES | C74: LUZ | D74: =+Iberdrola!B58 -> 3.0TD Plan Exclusivo 26/30%TE | E74: 3.0 | F74: =+Iberdrola!C58/365 -> 0.062199627 | G74: =+Iberdrola!D58/365 -> 0.033076403 | H74: =+Iberdrola!E58/365 -> 0.021533203 | I74: =+Iberdrola!F58/365 -> 0.015845605 | J74: =+Iberdrola!G58/365 -> 0.0094946384 | K74: =+Iberdrola!H58/365 -> 0.0066298438 | M74: =+Iberdrola!I58 -> 0.27836 | N74: =+Iberdrola!I58 -> 0.27836 | O74: =+Iberdrola!I58 -> 0.27836 | P74: =+Iberdrola!J58 -> 0.246127 | Q74: =+Iberdrola!K58 -> 0.214945 | R74: =+Iberdrola!L58 -> 0.187645 | T74: 0.15 | U74: =+Iberdrola!O57 -> 15% s/Te | X74: =+Iberdrola!P58 -> 0.03 | Z74: SELLO DE FECHA Y HORA
A75: IBERDROLA | B75: PYMES | C75: LUZ | D75: =+Iberdrola!B59 -> 3.0TD Empresas 10%TE | E75: 3.0 | F75: =+Iberdrola!C59/365 -> 0.055852079 | G75: =+Iberdrola!D59/365 -> 0.029101825 | H75: =+Iberdrola!E59/365 -> 0.012287222 | I75: =+Iberdrola!F59/365 -> 0.010656534 | J75: =+Iberdrola!G59/365 -> 0.0068963096 | K75: =+Iberdrola!H59/365 -> 0.0039556192 | M75: =+Iberdrola!I59 -> 0.226429 | N75: =+Iberdrola!I59 -> 0.226429 | O75: =+Iberdrola!I59 -> 0.226429 | P75: =+Iberdrola!J59 -> 0.188555 | Q75: =+Iberdrola!K59 -> 0.160055 | R75: =+Iberdrola!L59 -> 0.139455 | T75: 0.26 | U75: =+Iberdrola!O58 -> 26% ó 30% s/Te | X75: =+Iberdrola!P59 -> 0.01 | Z75: SELLO DE FECHA Y HORA
A76: IBERDROLA | B76: PYMES | C76: LUZ | D76: =+Iberdrola!B60 -> 3.0TD Empresa Plus | E76: 3.0 | F76: =+Iberdrola!C60/365 -> 0.055852079 | G76: =+Iberdrola!D60/365 -> 0.029101825 | H76: =+Iberdrola!E60/365 -> 0.012287222 | I76: =+Iberdrola!F60/365 -> 0.010656534 | J76: =+Iberdrola!G60/365 -> 0.0068963096 | K76: =+Iberdrola!H60/365 -> 0.0039556192 | M76: =+Iberdrola!I60 -> 0.211765 | N76: =+Iberdrola!I60 -> 0.211765 | O76: =+Iberdrola!I60 -> 0.211765 | P76: =+Iberdrola!J60 -> 0.178043 | Q76: =+Iberdrola!K60 -> 0.15556 | R76: =+Iberdrola!L60 -> 0.135386 | T76: 0.1 | U76: =+Iberdrola!O59 -> 10% s/Te | X76: =+Iberdrola!P60 -> 0.01 | Z76: SELLO DE FECHA Y HORA
A77: IBERDROLA | B77: PYMES | C77: LUZ | D77: =+Iberdrola!B61 -> 3.0TD Plan Especial 15%TE | E77: 3.0 | F77: =+Iberdrola!C61/365 -> 0.055852079 | G77: =+Iberdrola!D61/365 -> 0.029101825 | H77: =+Iberdrola!E61/365 -> 0.012287222 | I77: =+Iberdrola!F61/365 -> 0.010656534 | J77: =+Iberdrola!G61/365 -> 0.0068963096 | K77: =+Iberdrola!H61/365 -> 0.0039556192 | M77: =+Iberdrola!I61 -> 0.229475 | N77: =+Iberdrola!I61 -> 0.229475 | O77: =+Iberdrola!I61 -> 0.229475 | P77: =+Iberdrola!J61 -> 0.187326 | Q77: =+Iberdrola!K61 -> 0.159781 | R77: =+Iberdrola!L61 -> 0.138408 | U77: =+Iberdrola!O60 -> dto 0,02€/Kwh si consumo >40MWh/a | X77: =+Iberdrola!P61 -> 0.01 | Z77: SELLO DE FECHA Y HORA
A78: IBERDROLA | B78: PYMES | C78: LUZ | D78: =+Iberdrola!B62 -> 3.0TD Plan Verde 15%TE | E78: 3.0 | F78: =+Iberdrola!C62/365 -> 0.06223394 | G78: =+Iberdrola!D62/365 -> 0.040068668 | H78: =+Iberdrola!E62/365 -> 0.027062238 | I78: =+Iberdrola!F62/365 -> 0.021057323 | J78: =+Iberdrola!G62/365 -> 0.014804244 | K78: =+Iberdrola!H62/365 -> 0.010912775 | M78: =+Iberdrola!I62 -> 0.2268352 | N78: =+Iberdrola!I62 -> 0.2268352 | O78: =+Iberdrola!I62 -> 0.2268352 | P78: =+Iberdrola!J62 -> 0.1906194 | Q78: =+Iberdrola!K62 -> 0.1651216 | R78: =+Iberdrola!L62 -> 0.13839905 | T78: 0.15 | U78: =+Iberdrola!O61 -> 15% s/Te | X78: =+Iberdrola!P62 -> 0.03 | Z78: SELLO DE FECHA Y HORA
A79: IBERDROLA | B79: PYMES | C79: LUZ | D79: =+Iberdrola!B63 -> 3.0TD Plan OMIE 0 | E79: 3.0 | F79: =+Iberdrola!C63/365 -> 0.055852079 | G79: =+Iberdrola!D63/365 -> 0.029101825 | H79: =+Iberdrola!E63/365 -> 0.012287222 | I79: =+Iberdrola!F63/365 -> 0.010656534 | J79: =+Iberdrola!G63/365 -> 0.0068963096 | K79: =+Iberdrola!H63/365 -> 0.0039556192 | M79: =+Iberdrola!I63 -> 0.032 | N79: =+Iberdrola!I63 -> 0.032 | O79: =+Iberdrola!I63 -> 0.032 | T79: 0.15 | U79: =+Iberdrola!O62 -> 15% s/Te | X79: =+Iberdrola!P63 -> PVPC | Z79: SELLO DE FECHA Y HORA
A80: IBERDROLA | B80: PYMES | C80: LUZ | D80: =+Iberdrola!B64 -> 3.0TD Plan OMIE 1 | E80: 3.0 | F80: =+Iberdrola!C64/365 -> 0.055852079 | G80: =+Iberdrola!D64/365 -> 0.029101825 | H80: =+Iberdrola!E64/365 -> 0.012287222 | I80: =+Iberdrola!F64/365 -> 0.010656534 | J80: =+Iberdrola!G64/365 -> 0.0068963096 | K80: =+Iberdrola!H64/365 -> 0.0039556192 | M80: =+Iberdrola!I64 -> 0.026 | N80: =+Iberdrola!I64 -> 0.026 | O80: =+Iberdrola!I64 -> 0.026 | U80: =+Iberdrola!O63 -> s/ dto | X80: =+Iberdrola!P64 -> PVPC | Z80: SELLO DE FECHA Y HORA
A81: IBERDROLA | B81: PYMES | C81: LUZ | D81: =+Iberdrola!B65 -> 3.0TD Plan OMIE 2 | E81: 3.0 | F81: =+Iberdrola!C65/365 -> 0.055852079 | G81: =+Iberdrola!D65/365 -> 0.029101825 | H81: =+Iberdrola!E65/365 -> 0.012287222 | I81: =+Iberdrola!F65/365 -> 0.010656534 | J81: =+Iberdrola!G65/365 -> 0.0068963096 | K81: =+Iberdrola!H65/365 -> 0.0039556192 | M81: =+Iberdrola!I65 -> 0.02 | N81: =+Iberdrola!I65 -> 0.02 | O81: =+Iberdrola!I65 -> 0.02 | U81: =+Iberdrola!O64 -> s/ dto | X81: =+Iberdrola!P65 -> PVPC | Z81: SELLO DE FECHA Y HORA
A82: IBERDROLA | B82: PYMES | C82: LUZ | D82: =+Iberdrola!B66 -> 3.0TD Plan OMIE 3 | E82: 3.0 | F82: =+Iberdrola!C66/365 -> 0.055852079 | G82: =+Iberdrola!D66/365 -> 0.029101825 | H82: =+Iberdrola!E66/365 -> 0.012287222 | I82: =+Iberdrola!F66/365 -> 0.010656534 | J82: =+Iberdrola!G66/365 -> 0.0068963096 | K82: =+Iberdrola!H66/365 -> 0.0039556192 | M82: =+Iberdrola!I66 -> 0.01 | N82: =+Iberdrola!I66 -> 0.01 | O82: =+Iberdrola!I66 -> 0.01 | U82: =+Iberdrola!O65 -> s/ dto | X82: =+Iberdrola!P66 -> PVPC | Z82: SELLO DE FECHA Y HORA
A83: IBERDROLA | B83: PYMES | C83: LUZ | D83: =+Iberdrola!B67 -> 3.0TD Eventual/Temporal (s/IE) | E83: 3.0 | F83: =+Iberdrola!C67/365 -> 0.10308689 | G83: =+Iberdrola!D67/365 -> 0.070037877 | H83: =+Iberdrola!E67/365 -> 0.026028575 | I83: =+Iberdrola!F67/365 -> 0.022508422 | J83: =+Iberdrola!G67/365 -> 0.014452236 | K83: =+Iberdrola!H67/365 -> 0.0101258 | M83: =+Iberdrola!I67 -> 0.354832 | N83: =+Iberdrola!I67 -> 0.354832 | O83: =+Iberdrola!I67 -> 0.354832 | P83: =+Iberdrola!J67 -> 0.325068 | Q83: =+Iberdrola!K67 -> 0.297022 | R83: =+Iberdrola!L67 -> 0.280872 | U83: =+Iberdrola!O66 -> s/ dto | X83: =+Iberdrola!P67 -> 0.03 | Z83: SELLO DE FECHA Y HORA
A84: IBERDROLA | B84: PYMES | C84: LUZ | D84: =+Iberdrola!B71 -> 6.1TD Plan Exclusivo 15%TE | E84: 6.1 | F84: =+Iberdrola!C71/365 -> 0.081109027 | G84: =+Iberdrola!D71/365 -> 0.042518978 | H84: =+Iberdrola!E71/365 -> 0.018644685 | I84: =+Iberdrola!F71/365 -> 0.014787008 | J84: =+Iberdrola!G71/365 -> 0.0058316219 | K84: =+Iberdrola!H71/365 -> 0.0027554877 | M84: =+Iberdrola!I71 -> 0.208516 | N84: =+Iberdrola!I71 -> 0.208516 | O84: =+Iberdrola!I71 -> 0.208516 | P84: =+Iberdrola!J71 -> 0.17828 | Q84: =+Iberdrola!K71 -> 0.160093 | R84: =+Iberdrola!L71 -> 0.14599 | U84: =+Iberdrola!O70 -> 0 | X84: =+Iberdrola!P71 -> 0.05 | Z84: SELLO DE FECHA Y HORA
A85: IBERDROLA | B85: PYMES | C85: LUZ | D85: =+Iberdrola!B72 -> 6.1TD Empresas 10%TE | E85: 6.1 | F85: =+Iberdrola!C72/365 -> 0.081109027 | G85: =+Iberdrola!D72/365 -> 0.042518978 | H85: =+Iberdrola!E72/365 -> 0.018644685 | I85: =+Iberdrola!F72/365 -> 0.014787008 | J85: =+Iberdrola!G72/365 -> 0.0058316219 | K85: =+Iberdrola!H72/365 -> 0.0027554877 | M85: =+Iberdrola!I72 -> 0.18563 | N85: =+Iberdrola!I72 -> 0.18563 | O85: =+Iberdrola!I72 -> 0.18563 | P85: =+Iberdrola!J72 -> 0.160044 | Q85: =+Iberdrola!K72 -> 0.140496 | R85: =+Iberdrola!L72 -> 0.127006 | T85: 0.15 | U85: =+Iberdrola!O71 -> 15% s/Te | X85: =+Iberdrola!P72 -> 0.01 | Z85: SELLO DE FECHA Y HORA
A86: IBERDROLA | B86: PYMES | C86: LUZ | D86: =+Iberdrola!B73 -> 6.1TD Plan Especial 15%TE | E86: 6.1 | F86: =+Iberdrola!C73/365 -> 0.081109027 | G86: =+Iberdrola!D73/365 -> 0.042518978 | H86: =+Iberdrola!E73/365 -> 0.018644685 | I86: =+Iberdrola!F73/365 -> 0.014787008 | J86: =+Iberdrola!G73/365 -> 0.0058316219 | K86: =+Iberdrola!H73/365 -> 0.0027554877 | M86: =+Iberdrola!I73 -> 0.196632 | N86: =+Iberdrola!I73 -> 0.196632 | O86: =+Iberdrola!I73 -> 0.196632 | P86: =+Iberdrola!J73 -> 0.160545 | Q86: =+Iberdrola!K73 -> 0.135931 | R86: =+Iberdrola!L73 -> 0.121418 | T86: 0.1 | U86: =+Iberdrola!O72 -> 10% s/Te | X86: =+Iberdrola!P73 -> 0.01 | Z86: SELLO DE FECHA Y HORA
A87: IBERDROLA | B87: PYMES | C87: LUZ | D87: =+Iberdrola!B74 -> 6.1TD Empresa Plus | E87: 6.1 | F87: =+Iberdrola!C74/365 -> 0.081109027 | G87: =+Iberdrola!D74/365 -> 0.042518978 | H87: =+Iberdrola!E74/365 -> 0.018644685 | I87: =+Iberdrola!F74/365 -> 0.014787008 | J87: =+Iberdrola!G74/365 -> 0.0058316219 | K87: =+Iberdrola!H74/365 -> 0.0027554877 | M87: =+Iberdrola!I74 -> 0.173912 | N87: =+Iberdrola!I74 -> 0.173912 | O87: =+Iberdrola!I74 -> 0.173912 | P87: =+Iberdrola!J74 -> 0.144547 | Q87: =+Iberdrola!K74 -> 0.120947 | R87: =+Iberdrola!L74 -> 0.111999 | T87: 0.15 | U87: =+Iberdrola!O73 -> 15% s/Te | X87: =+Iberdrola!P74 -> 0.01 | Z87: SELLO DE FECHA Y HORA
A88: IBERDROLA | B88: PYMES | C88: LUZ | D88: =+Iberdrola!B75 -> 6.1TD Plan Verde 15%TE | E88: 6.1 | F88: =+Iberdrola!C75/365 -> 0.083848753 | G88: =+Iberdrola!D75/365 -> 0.045258704 | H88: =+Iberdrola!E75/365 -> 0.021384411 | I88: =+Iberdrola!F75/365 -> 0.017526734 | J88: =+Iberdrola!G75/365 -> 0.0085713479 | K88: =+Iberdrola!H75/365 -> 0.0054952137 | M88: =+Iberdrola!I75 -> 0.197438 | N88: =+Iberdrola!I75 -> 0.197438 | O88: =+Iberdrola!I75 -> 0.197438 | P88: =+Iberdrola!J75 -> 0.165452 | Q88: =+Iberdrola!K75 -> 0.145955 | R88: =+Iberdrola!L75 -> 0.132499 | U88: =+Iberdrola!O74 -> dto 0,01€/Kwh si consumo >100MWh/a | X88: =+Iberdrola!P75 -> 0.03 | Z88: SELLO DE FECHA Y HORA
A89: IBERDROLA | B89: PYMES | C89: LUZ | D89: =+Iberdrola!B76 -> 6.1TD Plan Regantes | E89: 6.1 | F89: =+Iberdrola!C76/365 -> 0.081109027 | G89: =+Iberdrola!D76/365 -> 0.042518978 | H89: =+Iberdrola!E76/365 -> 0.018644685 | I89: =+Iberdrola!F76/365 -> 0.014787008 | J89: =+Iberdrola!G76/365 -> 0.0058316219 | K89: =+Iberdrola!H76/365 -> 0.0027554877 | M89: =+Iberdrola!I76 -> 0.194442 | N89: =+Iberdrola!I76 -> 0.194442 | O89: =+Iberdrola!I76 -> 0.194442 | P89: =+Iberdrola!J76 -> 0.17037 | Q89: =+Iberdrola!K76 -> 0.156321 | R89: =+Iberdrola!L76 -> 0.132311 | T89: 0.15 | U89: =+Iberdrola!O75 -> 15% s/Te | X89: =+Iberdrola!P76 -> 0.03 | Z89: SELLO DE FECHA Y HORA
A90: IBERDROLA | B90: PYMES | C90: LUZ | D90: =+Iberdrola!B77 -> 6.1TD Plan OMIE 0 | E90: 6.1 | F90: =+Iberdrola!C77/365 -> 0.081109027 | G90: =+Iberdrola!D77/365 -> 0.042518978 | H90: =+Iberdrola!E77/365 -> 0.018644685 | I90: =+Iberdrola!F77/365 -> 0.014787008 | J90: =+Iberdrola!G77/365 -> 0.0058316219 | K90: =+Iberdrola!H77/365 -> 0.0027554877 | M90: =+Iberdrola!I77 -> 0.01 | N90: =+Iberdrola!I77 -> 0.01 | O90: =+Iberdrola!I77 -> 0.01 | U90: =+Iberdrola!O76 -> s/ dto | X90: =+Iberdrola!P77 -> PVPC | Z90: SELLO DE FECHA Y HORA
A91: IBERDROLA | B91: PYMES | C91: LUZ | D91: =+Iberdrola!B78 -> 6.1TD Plan OMIE 2 | E91: 6.1 | F91: =+Iberdrola!C78/365 -> 0.081109027 | G91: =+Iberdrola!D78/365 -> 0.042518978 | H91: =+Iberdrola!E78/365 -> 0.018644685 | I91: =+Iberdrola!F78/365 -> 0.014787008 | J91: =+Iberdrola!G78/365 -> 0.0058316219 | K91: =+Iberdrola!H78/365 -> 0.0027554877 | M91: =+Iberdrola!I78 -> 0.005 | N91: =+Iberdrola!I78 -> 0.005 | O91: =+Iberdrola!I78 -> 0.005 | U91: =+Iberdrola!O77 -> s/ dto | X91: =+Iberdrola!P78 -> PVPC | Z91: SELLO DE FECHA Y HORA
A92: IBERDROLA | B92: PYMES | C92: LUZ | D92: =+Iberdrola!B79 -> 6.1TD Eventual/Temporal (s/IE) | E92: 6.1 | F92: =+Iberdrola!C79/365 -> 0.15113855 | G92: =+Iberdrola!D79/365 -> 0.1208213 | H92: =+Iberdrola!E79/365 -> 0.059495781 | I92: =+Iberdrola!F79/365 -> 0.044153542 | J92: =+Iberdrola!G79/365 -> 0.0063170055 | K92: =+Iberdrola!H79/365 -> 0.003239 | M92: =+Iberdrola!I79 -> 0.278516 | N92: =+Iberdrola!I79 -> 0.278516 | O92: =+Iberdrola!I79 -> 0.278516 | P92: =+Iberdrola!J79 -> 0.24828 | Q92: =+Iberdrola!K79 -> 0.230093 | R92: =+Iberdrola!L79 -> 0.21599 | U92: =+Iberdrola!O78 -> s/ dto | X92: =+Iberdrola!P79 -> 0.03 | Z92: SELLO DE FECHA Y HORA
A93: IBERDROLA | B93: PYMES | C93: LUZ | D93: =+Iberdrola!B81 -> 6.2TD Plan OMIE 1 | E93: 6.1 | F93: =+Iberdrola!C81/365 -> 0.05509349 | G93: =+Iberdrola!D81/365 -> 0.030461477 | H93: =+Iberdrola!E81/365 -> 0.010167468 | I93: =+Iberdrola!F81/365 -> 0.0074799041 | J93: =+Iberdrola!G81/365 -> 0.0034729589 | K93: =+Iberdrola!H81/365 -> 0.0016611068 | M93: =+Iberdrola!I81 -> 0.01 | N93: =+Iberdrola!I81 -> 0.01 | O93: =+Iberdrola!I81 -> 0.01 | U93: =+Iberdrola!O80 -> 0 | X93: =+Iberdrola!P81 -> PVPC | Z93: SELLO DE FECHA Y HORA
A94: IBERDROLA | B94: PYMES | C94: LUZ | D94: =+Iberdrola!B82 -> 6.2TD Eventual/Temporal (s/IE) | E94: 6.1 | F94: =+Iberdrola!C82/365 -> 0.10645746 | G94: =+Iberdrola!D82/365 -> 0.086682751 | H94: =+Iberdrola!E82/365 -> 0.036603367 | I94: =+Iberdrola!F82/365 -> 0.030360038 | J94: =+Iberdrola!G82/365 -> 0.0038762548 | K94: =+Iberdrola!H82/365 -> 0.0020632932 | M94: =+Iberdrola!I82 -> 0.255078 | N94: =+Iberdrola!I82 -> 0.255078 | O94: =+Iberdrola!I82 -> 0.255078 | P94: =+Iberdrola!J82 -> 0.245531 | Q94: =+Iberdrola!K82 -> 0.23173 | R94: =+Iberdrola!L82 -> 0.223431 | U94: =+Iberdrola!O81 -> s/ dto | X94: =+Iberdrola!P82 -> 0.03 | Z94: SELLO DE FECHA Y HORA
A95: NIBA | B95: RESIDENCIAL | C95: LUZ | D95: ZEN | E95: 2.0 | F95: 0.097 | G95: 0.043 | M95: 0.12 | N95: =+Tabla1[[#This Row],[ENERGIA 1]] -> 0.12 | O95: =+Tabla1[[#This Row],[ENERGIA 2]] -> 0.12 | X95: 0.06 | Z95: SELLO DE FECHA Y HORA
A96: NIBA | B96: RESIDENCIAL | C96: LUZ | D96: TRES | E96: 2.0 | F96: 0.097 | G96: 0.043 | M96: 0.2 | N96: 0.118 | O96: 0.079 | X96: 0.06 | Z96: SELLO DE FECHA Y HORA
A97: NIBA | B97: RESIDENCIAL | C97: GAS | D97: ZEN | E97: RL.1 | L97: =6.03*0.0328767123287671 -> 0.19824658 | S97: 0.066 | Z97: SELLO DE FECHA Y HORA
A98: NIBA | B98: RESIDENCIAL | C98: GAS | D98: ZEN | E98: RL.2 | L98: =11.3*0.0328767123287671 -> 0.37150685 | S98: 0.068 | Z98: SELLO DE FECHA Y HORA
A99: NIBA | B99: RESIDENCIAL | C99: GAS | D99: ZEN | E99: RL.3 | L99: =20.71*0.0328767123287671 -> 0.68087671 | S99: 0.072 | Z99: SELLO DE FECHA Y HORA
A100: NIBA | B100: PYMES | C100: LUZ | D100: COMUNIDADES | E100: 2.0 | F100: 0.095 | G100: 0.04 | M100: 0.129 | N100: =+Tabla1[[#This Row],[ENERGIA 1]] -> 0.129 | O100: =+Tabla1[[#This Row],[ENERGIA 2]] -> 0.129 | X100: 0.06 | Z100: SELLO DE FECHA Y HORA
...

Sheet Naturgy Pymes
B4: ELECTRICIDAD
C6: PLAN FIJO LUZ 24h (E0008) | L6: M | S6: B | Z6: A
L7: Plan Fijo Luz 24h TÉRMINO ENERGÍA (€/kWh) | R7: PFL ONE | S7: Plan Fijo Luz 24h ONE TÉRMINO ENERGÍA (€/kWh) | Y7: PFL SUPRA | Z7: Plan Fijo Luz 24h SUPRA TÉRMINO ENERGÍA (€/kWh)
E8: Consumo hasta: (kWh/año) | F8: P. TÉRMINO POTENCIA (€/kW.día)
F9: P1 | G9: P2 | H9: P3 | I9: P4 | J9: P5 | K9: P6 | L9: P1 | M9: P2 | N9: P3 | O9: P4 | P9: P5 | Q9: P6 | S9: P1 | T9: P2 | U9: P3 | V9: P4 | W9: P5 | X9: P6 | Z9: P1 | AA9: P2 | AB9: P3 | AC9: P4 | AD9: P5 | AE9: P6
A10: E000820TDM | B10: E0008 | C10: 20TD | D10: Plan Fijo Luz 24h 2.0 | E10: 9999999999 | F10: 0.12297298 | G10: 0.043976022 | L10: 0.136171 | R10: E000820TDB | S10: 0.120671 | Y10: E000820TDA | Z10: 0.149171 | AF10: E0008PFL ONE19999999999 | AG10: E0008PFL SUPRA19999999999
C13: PLAN FIJO LUZ (E0009) | L13: M | S13: B | Z13: A
L14: Plan Fijo Luz TÉRMINO ENERGÍA (€/kWh) | R14: PFL ONE | S14: Plan Fijo Luz ONE TÉRMINO ENERGÍA (€/kWh) | Y14: PFL SUPRA | Z14: Plan Fijo Luz SUPRA TÉRMINO ENERGÍA (€/kWh)
E15: Consumo hasta: (kWh/año) | F15: P. TÉRMINO POTENCIA (€/kW.día)
F16: P1 | G16: P2 | H16: P3 | I16: P4 | J16: P5 | K16: P6 | L16: P1 | M16: P2 | N16: P3 | O16: P4 | P16: P5 | Q16: P6 | S16: P1 | T16: P2 | U16: P3 | V16: P4 | W16: P5 | X16: P6 | Z16: P1 | AA16: P2 | AB16: P3 | AC16: P4 | AD16: P5 | AE16: P6
A17: E000920TDM | B17: E0009 | C17: 20TD | D17: Plan Fijo Luz 2.0 TRIHORARIO | E17: 9999999999 | F17: 0.12297298 | G17: 0.043976022 | L17: 0.206464 | M17: 0.133311 | N17: 0.097973 | R17: E000920TDB | S17: 0.190964 | T17: 0.117811 | U17: 0.082473 | Y17: E000920TDA | Z17: 0.219465 | AA17: 0.146312 | AB17: 0.110973 | AF17: E0009PFL ONE19999999999 | AG17: E0009PFL SUPRA19999999999
A18: E000930TDM | B18: E0009 | C18: 30TD | D18: Plan Fijo Luz 3.0 | E18: 9999999999 | F18: 0.057927649 | G18: 0.031189775 | H18: 0.014378597 | I18: 0.012747912 | J18: 0.0089877041 | K18: 0.0060519452 | L18: 0.195993 | M18: 0.170414 | N18: 0.147424 | O18: 0.133736 | P18: 0.127043 | Q18: 0.119208 | R18: E000930TDB | S18: 0.183593 | T18: 0.158014 | U18: 0.134925 | V18: 0.121236 | W18: 0.114444 | X18: 0.106808 | Y18: E000930TDA | Z18: 0.215493 | AA18: 0.189914 | AB18: 0.166925 | AC18: 0.153235 | AD18: 0.146543 | AE18: 0.138708 | AF18: E0009PFL ONE19999999999 | AG18: E0009PFL SUPRA19999999999
A19: E000961TDM | B19: E0009 | C19: 61TD | D19: Plan Fijo Luz 6.1 | E19: 9999999999 | F19: 0.081083211 | G19: 0.042506038 | H19: 0.018635277 | I19: 0.014777622 | J19: 0.0058222356 | K19: 0.002751189 | L19: 0.170106 | M19: 0.149355 | N19: 0.133961 | O19: 0.124135 | P19: 0.117561 | Q19: 0.111182 | R19: E000961TDB | S19: 0.158307 | T19: 0.137456 | U19: 0.122062 | V19: 0.112235 | W19: 0.105661 | X19: 0.099383 | Y19: E000961TDA | Z19: 0.189606 | AA19: 0.168856 | AB19: 0.153461 | AC19: 0.143635 | AD19: 0.13706 | AE19: 0.130683 | AF19: E0009PFL ONE19999999999 | AG19: E0009PFL SUPRA19999999999
Z20: 0.11 | AA20: 0.13 | AB20: 0.13 | AC20: 0.14 | AD20: 0.05 | AE20: 0.44
C21: PLAN FIJO LUZ ECO (E0010) | L21: M | S21: B | Z21: A
C22: 0.0094 | L22: Plan Fijo Luz ECO TÉRMINO ENERGÍA (€/kWh) | R22: PFL ONE | S22: Plan Fijo Luz ECO ONE TÉRMINO ENERGÍA (€/kWh) | Y22: PFL SUPRA | Z22: Plan Fijo Luz ECO SUPRA TÉRMINO ENERGÍA (€/kWh)
E23: Consumo hasta: (kWh/año) | F23: P. TÉRMINO POTENCIA (€/kW.día)
F24: P1 | G24: P2 | H24: P3 | I24: P4 | J24: P5 | K24: P6 | L24: P1 | M24: P2 | N24: P3 | O24: P4 | P24: P5 | Q24: P6 | S24: P1 | T24: P2 | U24: P3 | V24: P4 | W24: P5 | X24: P6 | Z24: P1 | AA24: P2 | AB24: P3 | AC24: P4 | AD24: P5 | AE24: P6
A25: E001020TDM | B25: E0010 | C25: 20TD | D25: Plan Fijo Luz ECO 2.0 TRIHORARIO | E25: 9999999999 | F25: 0.12297298 | G25: 0.043976022 | L25: 0.209975 | M25: 0.136822 | N25: 0.101483 | R25: E001020TDB | S25: 0.194475 | T25: 0.121322 | U25: 0.085983 | Y25: E001020TDA | Z25: 0.222975 | AA25: 0.149822 | AB25: 0.114483 | AF25: E0010PFL ONE19999999999 | AG25: E0010PFL SUPRA19999999999
A26: E001030TDM | B26: E0010 | C26: 30TD | D26: Plan Fijo Luz ECO 3.0 | E26: 9999999999 | F26: 0.057927649 | G26: 0.031189775 | H26: 0.014378597 | I26: 0.012747912 | J26: 0.0089877041 | K26: 0.0060519452 | L26: 0.199503 | M26: 0.173924 | N26: 0.150935 | O26: 0.137245 | P26: 0.130553 | Q26: 0.122718 | R26: E001030TDB | S26: 0.187103 | T26: 0.161524 | U26: 0.138435 | V26: 0.124746 | W26: 0.117954 | X26: 0.110318 | Y26: E001030TDA | Z26: 0.219003 | AA26: 0.193424 | AB26: 0.170435 | AC26: 0.156745 | AD26: 0.150053 | AE26: 0.142218 | AF26: E0010PFL ONE19999999999 | AG26: E0010PFL SUPRA19999999999
A27: E001061TDM | B27: E0010 | C27: 61TD | D27: Plan Fijo Luz ECO 6.1 | E27: 9999999999 | F27: 0.081083211 | G27: 0.042506038 | H27: 0.018635277 | I27: 0.014777622 | J27: 0.0058222356 | K27: 0.002751189 | L27: 0.173616 | M27: 0.152866 | N27: 0.137471 | O27: 0.127645 | P27: 0.12107 | Q27: 0.114693 | R27: E001061TDB | S27: 0.161817 | T27: 0.140966 | U27: 0.125572 | V27: 0.115745 | W27: 0.109171 | X27: 0.102893 | Y27: E001061TDA | Z27: 0.193116 | AA27: 0.172366 | AB27: 0.156971 | AC27: 0.147145 | AD27: 0.14057 | AE27: 0.134193 | AF27: E0010PFL ONE19999999999 | AG27: E0010PFL SUPRA19999999999
C29: PLAN VARIABLE LUZ (E0013)
L30: Plan Variable Luz TÉRMINO ENERGÍA (€/kWh) | R30: PNM ONE | S30: Plan Variable Luz ONE TÉRMINO ENERGÍA (€/kWh) | Y30: PFL SUPRA | Z30: Plan Variable Luz SUPRA TÉRMINO ENERGÍA (€/kWh)
E31: Consumo hasta: (kWh/año) | F31: P. TÉRMINO POTENCIA (€/kW.día)
F32: P1 | G32: P2 | H32: P3 | I32: P4 | J32: P5 | K32: P6 | L32: P1 | M32: P2 | N32: P3 | O32: P4 | P32: P5 | Q32: P6 | S32: P1 | T32: P2 | U32: P3 | V32: P4 | W32: P5 | X32: P6 | Z32: P1 | AA32: P2 | AB32: P3 | AC32: P4 | AD32: P5 | AE32: P6
A33: 20TD | B33: 42053 | C33: 2.0TD | D33: Plan Variable Luz 2.0 | E33: 9999999999 | F33: 0.079327162 | G33: 0.0054121205 | L33: 0.258866 | M33: 0.183799 | N33: 0.139187 | S33: 0.243366 | T33: 0.168299 | U33: 0.123687 | Y33: -6 | Z33: 0.264866 | AA33: 0.189799 | AB33: 0.145187
A34: 30TD | B34: 42055 | C34: 3.0TD | D34: Plan Variable Luz 3.0 | E34: 9999999999 | F34: 0.056283827 | G34: 0.029545995 | H34: 0.012734797 | I34: 0.01110411 | J34: 0.0073438849 | K34: 0.0044081041 | L34: 0.222898 | M34: 0.196761 | Q34: 0.141847 | S34: 0.207398 | T34: 0.181261 | X34: 0.126347 | Z34: 0.228898 | AA34: 0.202761 | AE34: 0.147847
A35: 61TD | B35: 42057 | C35: 6.1TD | D35: Plan Variable Luz 6X | E35: 9999999999 | F35: 0.0810832 | G35: 0.042506052 | H35: 0.01863529 | I35: 0.014777614 | J35: 0.0058222274 | K35: 0.0027511808 | L35: 0.194917 | M35: 0.172743 | Q35: 0.130985 | S35: 0.179417 | T35: 0.157243 | X35: 0.115485 | Z35: 0.200917 | AA35: 0.178743 | AE35: 0.136985
C38: TEMPORADA/OBRA
E40: Consumo hasta: (kWh/año) | F40: P. TÉRMINO POTENCIA (€/kW.día) | L40: P. TÉRMINO ENERGÍA (€/kWh)
F41: P1 | G41: P2 | H41: P3 | I41: P4 | J41: P5 | K41: P6 | L41: P1 | M41: P2 | N41: P3 | O41: P4 | P41: P5 | Q41: P6
A42: 4200919999999999 | B42: 42009 | C42: 2.0TD | D42: Contrato Temporada/Obra 2.0TD | E42: 9999999999 | F42: #N/A | G42: #N/A | H42: #N/A | I42: #N/A | J42: #N/A | K42: #N/A | L42: #N/A | M42: #N/A | N42: #N/A | O42: #N/A | P42: #N/A | Q42: #N/A
A43: 4202319999999999 | B43: 42023 | C43: 2.0TD Trihoraria | D43: Contrato Temporada/Obra Trihorario 2.0TD | E43: 9999999999 | F43: #N/A | G43: #N/A | H43: #N/A | I43: #N/A | J43: #N/A | K43: #N/A | L43: #N/A | M43: #N/A | N43: #N/A | O43: #N/A | P43: #N/A | Q43: #N/A
A44: 4203819999999999 | B44: 42038 | C44: 3.0TD | D44: Contrato Temporada/Obra 3.0TD | E44: 9999999999 | F44: #N/A | G44: #N/A | H44: #N/A | I44: #N/A | J44: #N/A | K44: #N/A | L44: #N/A | M44: #N/A | N44: #N/A | O44: #N/A | P44: #N/A | Q44: #N/A
A45: 4205019999999999 | B45: 42050 | C45: 6.1TD | D45: Contrato Temporada/Obra 6.XTD | E45: 9999999999 | F45: #N/A | G45: #N/A | H45: #N/A | I45: #N/A | J45: #N/A | K45: #N/A | L45: #N/A | M45: #N/A | N45: #N/A | O45: #N/A | P45: #N/A | Q45: #N/A
B48: GAS
C50: PLAN VARIABLE GAS (G0009) | G50: PLAN VARIABLE GAS SUPRA | I50: PLAN VARIABLE GAS | K50: PLAN VARIABLE GAS ONE
G52: Sin Dto | H52: A | I52: Dto 3€/MWh TV | K52: Dto 8€/MWh TV
E53: Consumo hasta: (kWh/año) | F53: PRECIO TÉRMINO FIJO (€/día/cliente) | H53: PRECIO TÉRMINO VARIABLE (€/kWh) | J53: PRECIO TÉRMINO VARIABLE (€/kWh) | L53: PRECIO TÉRMINO VARIABLE (€/kWh)
A55: G0009RL.1A | B55: G0009 | C55: RL.1 | D55: PLAN VARIABLE GAS MENSUAL | E55: 5000 | F55: 0.080382093 | G55: 0 | H55: 0.056145 | I55: 3 | J55: 0.053145 | K55: 8 | L55: 0.048145
A56: G0009RL.2A | B56: G0009 | C56: RL.2 | D56: PLAN VARIABLE GAS MENSUAL | E56: 15000 | F56: 0.21185583 | H56: 0.054046 | J56: 0.051046 | L56: 0.046046
A57: G0009RL.3A | B57: G0009 | C57: RL.3 | D57: PLAN VARIABLE GAS MENSUAL | E57: 50000 | F57: 0.56067564 | H57: 0.050606 | J57: 0.047606 | L57: 0.042606
A58: G0009RL.4A | B58: G0009 | C58: RL.4 | D58: PLAN VARIABLE GAS MENSUAL | E58: 300000 | F58: 1.3686556 | H58: 0.05469 | J58: 0.05169 | L58: 0.04669
A59: G0009RL.5A | B59: G0009 | C59: RL.5 | D59: PLAN VARIABLE GAS MENSUAL | E59: 1500000 | F59: 7.6385029 | H59: 0.054627 | J59: 0.051627 | L59: 0.046627
C61: PLAN COMPROMISO GAS (G0007) | G61: PLAN COMPROMISO GAS | I61: PLAN COMPROMISO GAS SUPRA
G63: Dto 9€/MWh TV | H63: M | I63: Dto 3€/MWh TV | J63: A
E64: Consumo hasta: (kWh/año) | F64: PRECIO TÉRMINO FIJO (€/día/cliente) | H64: PRECIO TÉRMINO VARIABLE (€/kWh) | J64: PRECIO TÉRMINO VARIABLE (€/kWh)
A66: G0007RL.1A | B66: G0007 | C66: RL.1 | D66: PLAN COMPROMISO GAS | E66: 5000 | F66: 0.080382093 | G66: 6.1 | H66: 0.060064 | I66: 3 | J66: 0.066164
A67: G0007RL.2A | B67: G0007 | C67: RL.2 | D67: PLAN COMPROMISO GAS | E67: 15000 | F67: 0.21185583 | H67: 0.057965 | J67: 0.064065
A68: G0007RL.3A | B68: G0007 | C68: RL.3 | D68: PLAN COMPROMISO GAS | E68: 50000 | F68: 0.56067564 | H68: 0.054525 | J68: 0.060625
A69: G0007RL.4A | B69: G0007 | C69: RL.4 | D69: PLAN COMPROMISO GAS | E69: 300000 | F69: 1.3686556 | H69: 0.058609 | J69: 0.064709
A70: G0007RL.5A | B70: G0007 | C70: RL.5 | D70: PLAN COMPROMISO GAS | E70: 1500000 | F70: 7.6385029 | H70: 0.058546 | J70: 0.064646
B73: SERVICIOS
K74: IVA = | L74: 0.21 | Q74: IGIC = | R74: 0.07
E75: SIN IMPUESTOS | J75: CON IMPUESTOS PENINSULA y BALEARES | O75: CON IMPUESTOS CANARIAS
C76: SVG GC Complet (RL.4/RL.5) | E76: 179.45 | F76: Dto. | G76: 0.2 | H76: 143.56 | J76: 217.1345 | K76: Dto. | L76: 0.2 | M76: 173.7076 | O76: 192.0115 | Q76: Dto. | R76: 0.2 | S76: 153.6092
C77: SVE GC Xpress (20TD/30TD) | E77: 86.63 | F77: Dto. | G77: 0.2 | H77: 69.304 | J77: 104.8223 | K77: Dto. | L77: 0.2 | M77: 83.85784 | O77: 92.6941 | Q77: Dto. | R77: 0.2 | S77: 74.15528
C78: SVS GC <10kWp (2.0TD/3.0TD) | E78: 126.63 | F78: Dto. | G78: 0.2 | H78: 101.304 | J78: 153.2223 | K78: Dto. | L78: 0.2 | M78: 122.57784 | O78: 135.4941 | Q78: Dto. | R78: 0.2 | S78: 108.39528
C79: Batería Virtual | E79: 0 | J79: 0 | O79: 0

Sheet Iberdrola
B2: PRODUCTOS | C2: TERMINO DE POTENCIA (€/kW año) | I2: TERMINO DE ENERGIA (€/kWh) | O2: DESCUENTO | P2: Precio Excedentes | Q2: DURACION | R2: FACTURA ELECT. | S2: ENERGIA VERDE | T2: CANAL PRESEN | U2: TERMINO DE POTENCIA (€/kW dia)
C3: P1 | D3: P2 | E3: P3 | F3: P4 | G3: P5 | H3: P6 | I3: P1 | J3: P2 | K3: P3 | L3: P4 | M3: P5 | N3: P6 | U3: P1 | V3: P2
C4: Punta | D4: Valle | I4: Punta | J4: Llano | K4: Valle | U4: Punta | V4: Valle
I5: No Prom. | J5: Prom. | O5: % | P5: €/Kwh | Q5: (Precio/Dto) | R5: (Obligat.) | S5: (GdO) | T5: (S/N) | U5: €/kWdía | V5: €/kWdía
C6: 1 | D6: 2 | E6: 3 | F6: 4 | G6: 5 | H6: 6 | I6: 7 | J6: 8 | K6: 9 | L6: 10 | M6: 11 | N6: 12
B8: ELECTRICIDAD - 2.0TD [P1 =< 15kW] Baja Tensión
B9: 2.0TD _ 2 P1 <= 10kW
B10: 2.0TD_2 Plan Exclusivo 15%TE/TP 1p | C10: 42.99 | D10: 21.99 | I10: 0.207647 | O10: 15% s/Te y Tp (+5% si PIH / PEH+ / UUEEn/ Pack Bienestar) | P10: 0.06 | Q10: 12m | R10: N | S10: N | T10: S | U10: 0.11778082 | V10: 0.060246575
B11: 2.0TD_2 Plan Exclusivo 15%TE/TP 3p | C11: 42.99 | D11: 21.99 | I11: 0.2522 | J11: 0.2107 | K11: 0.1828 | O11: 15% s/Te y Tp (+5% si PIH / PEH+ / UUEEn/ Pack Bienestar) | P11: 0.06 | Q11: 12m | R11: N | S11: N | T11: S | U11: 0.11778082 | V11: 0.060246575
B12: 2.0TD_2 Plan Especial plus 15%TE 1p | C12: 39.49 | D12: 16.99 | I12: 0.14875 | O12: 15% s/Te (+5% si PIH / PEH+ / UUEEn/ Pack Bienestar) | P12: 0.06 | Q12: 12m | R12: N | S12: N | T12: S | U12: 0.10819178 | V12: 0.046547945
B13: 2.0TD_2 Plan Hogar Especial | C13: 31 | D13: 17.99 | I13: 0.191875 | O13: 15% s/Te (+5% si PIH / PEH+ / UUEEn/ Pack Bienestar) | P13: 0.06 | Q13: 36m / 12m | R13: N | S13: N | T13: S | U13: 0.084931507 | V13: 0.049287671
B14: 2.0TD_2 Plan Estable | C14: 39.49 | D14: 16.99 | I14: 0.174875 | O14: 15% s/Te (+5% si PIH / PEH+ / UUEEn/ Pack Bienestar) | P14: 0.06 | Q14: 60m / 12m | R14: S | S14: S | T14: S | U14: 0.10819178 | V14: 0.046547945
B15: 2.0TD_2 Planazo | C15: 39.49 | D15: 17.99 | I15: 0.191875 | O15: 15% s/Te (+5% si PIH / PEH+ / UUEEn/ Pack Bienestar) + 100€ en conciertos | P15: 0.06 | Q15: 60m / 12m | R15: S | S15: S | T15: S | U15: 0.10819178 | V15: 0.049287671
B16: 2.0TD_2 Plan Más Ahorro | C16: 39.49 | D16: 17.99 | I16: 0.171111 | O16: 10% / 15% / 20% /25% / 30% Te (+5% si PIH / PEH+ / UUEEn/ Pack Bienestar) | P16: 0.06 | Q16: 60m / 12m* | R16: S | S16: S | T16: S | U16: 0.10819178 | V16: 0.049287671
B17: 2.0TD_2 Plan Ahorro Inteligente 8 horas | C17: 39.49 | D17: 17.99 | I17: 0.23526 | J17: 0.11763 | O17: 15% s/Te (+5% si PIH / PEH+) | P17: 0.06 | Q17: 60m / 24m | R17: S | S17: S | T17: S | U17: 0.10819178 | V17: 0.049287671
B18: 2.0TD_2 Plan Ahorro Automático 100 | C18: 39.49 | D18: 17.99 | I18: 0.217 | O18: 100€ (+20€ si PIH / PEH+/ PI / PEH ); 50% dos días de más consumo | P18: 0.06 | Q18: 60m / 12m | R18: S | S18: S | T18: S | U18: 0.10819178 | V18: 0.049287671
B19: 2.0TD_2 Plan Verano | C19: 39.49 | D19: 17.99 | I19: 0.249822 | J19: 0.124911 | O19: 15% s/Tp (+5% si PIH / PEH+ / UUEEn/ Pack Bienestar) | P19: 0.06 | Q19: 60m / 12m | R19: S | S19: S | T19: S | U19: 0.10819178 | V19: 0.049287671
B20: 2.0TD_2 Plan Estable Comunidades de Propietarios | C20: 42.49 | D20: 18.99 | I20: 0.159131 | O20: 15% s/Te (+5% si ACP) + 5% s/te 2año | P20: 0.06 | Q20: 24m | R20: S | S20: S | T20: S | U20: 0.11641096 | V20: 0.052027397
B21: 2.0TD_2 Plan Solar | C21: 39.49 | D21: 17.99 | I21: 0.244 | J21: 0.122 | O21: s/ dto | P21: 0.06 | Q21: 12m | R21: S | S21: S | T21: S | U21: 0.10819178 | V21: 0.049287671
B22: 2.0TD_2 Plan Recarga Inteligente | C22: 39.49 | D22: 17.99 | I22: 0.149999 | O22: s/ dto | P22: 0.06 | Q22: 12m | R22: S | S22: S | T22: S | U22: 0.10819178 | V22: 0.049287671
B23: 2.0TD_2 Impulsa 24h | C23: 42.49 | D23: 16.99 | I23: 0.1732 | O23: 20% s/Te (+5% si PIH / PEH+ / UUEEn/ Pack Bienestar) | P23: 0.06 | Q23: 12m | R23: S | S23: N | T23: S | U23: 0.11641096 | V23: 0.046547945
B24: 2.0TD_2 Plan OMIE | C24: 26.93055 | D24: 0.697588 | I24: 0.015 | O24: s/ dto (únicamente para fidelización) | P24: PVPC | Q24: 12m | R24: N | S24: N | T24: S | U24: 0.073782329 | V24: 0.0019112
B25: 2.0TD_2 Plan OMIE Comunidades | C25: 26.93055 | D25: 0.697588 | I25: 0.03 | O25: s/ dto | P25: PVPC | Q25: 12m | R25: N | S25: N | T25: S | U25: 0.073782329 | V25: 0.0019112
B26: 2.0TD _ 3 P1 > 10kW
B27: 2.0TD_3 Plan Exclusivo 15%TE/TP 1p | C27: 42.99 | D27: 21.99 | I27: 0.207647 | O27: 15% s/Te y Tp (+5% si PIH / PEH+ / UUEEn/ Pack Bienestar) | P27: 0.06 | Q27: 12m | R27: N | S27: N | T27: S | U27: 0.11778082 | V27: 0.060246575
B28: 2.0TD_3 Plan Exclusivo 15%TE/TP 3p | C28: 42.99 | D28: 21.99 | I28: 0.2481 | J28: 0.2148 | K28: 0.2045 | O28: 15% s/Te y Tp (+5% si PIH / PEH+ / UUEEn/ Pack Bienestar) | P28: 0.06 | Q28: 12m | R28: N | S28: N | T28: S | U28: 0.11778082 | V28: 0.060246575
B29: 2.0TD_3 Plan Especial plus 15%TE 1p | C29: 39.49 | D29: 16.99 | I29: 0.15375 | O29: 15% s/Te (+5% si PIH / PEH+ / UUEEn/ Pack Bienestar) | P29: 0.06 | Q29: 12m | R29: N | S29: N | T29: S | U29: 0.10819178 | V29: 0.046547945
B30: 2.0TD_3 Plan Hogar Especial | C30: 31 | D30: 17.99 | I30: 0.196875 | O30: 15% s/Te (+5% si PIH / PEH+ / UUEEn/ Pack Bienestar) | P30: 0.06 | Q30: 36m / 12m | R30: N | S30: N | T30: S | U30: 0.084931507 | V30: 0.049287671
B31: 2.0TD_3 Plan Estable | C31: 39.49 | D31: 16.99 | I31: 0.174875 | O31: 15% s/Te (+5% si PIH / PEH+ / UUEEn/ Pack Bienestar) | P31: 0.06 | Q31: 60m / 12m | R31: S | S31: S | T31: S | U31: 0.10819178 | V31: 0.046547945
B32: 2.0TD_3 Planazo | C32: 39.49 | D32: 17.99 | I32: 0.191875 | O32: 15% s/Te (+5% si PIH / PEH+ / UUEEn/ Pack Bienestar) + 100€ en conciertos | P32: 0.06 | Q32: 60m / 12m | R32: S | S32: S | T32: S | U32: 0.10819178 | V32: 0.049287671
B33: 2.0TD_3 Plan Más Ahorro | C33: 39.49 | D33: 17.99 | I33: 0.181111 | O33: 10% / 15% / 20% /25% / 30% Te (+5% si PIH / PEH+ / UUEEn/ Pack Bienestar) | P33: 0.06 | Q33: 60m / 12m | R33: S | S33: S | T33: S | U33: 0.10819178 | V33: 0.049287671
B34: 2.0TD_3 Plan Ahorro Inteligente 8 horas | C34: 39.49 | D34: 17.99 | I34: 0.24526 | J34: 0.12263 | O34: 15% s/Te (+5% si PIH / PEH+ / UUEEn/ Pack Bienestar) | P34: 0.06 | Q34: 60m / 24m | R34: S | S34: S | T34: S | U34: 0.10819178 | V34: 0.049287671
B35: 2.0TD_3 Plan Ahorro Automático 100 | C35: 39.49 | D35: 17.99 | I35: 0.217 | O35: 100€ (+20€ si PIH / PEH+/ PI / PEH ) | P35: 0.06 | Q35: 60m / 12m | R35: S | S35: S | T35: S | U35: 0.10819178 | V35: 0.049287671
B36: 2.0TD_3 Plan Verano | C36: 39.49 | D36: 17.99 | I36: 0.249822 | J36: 0.124911 | O36: 15% s/Tp (+5% si PIH / PEH+ / UUEEn/ Pack Bienestar) | P36: 0.06 | Q36: 60m / 12m | R36: S | S36: S | T36: S | U36: 0.10819178 | V36: 0.049287671
B37: 2.0TD_3 Plan Estable Comunidades de Propietarios | C37: 42.49 | D37: 18.99 | I37: 0.159131 | O37: 15% s/Te (+5% si ACP) + 5% s/te 2año | P37: 0.06 | Q37: 24m | R37: S | S37: S | T37: S | U37: 0.11641096 | V37: 0.052027397
B38: 2.0TD_3 Plan Solar | C38: 39.49 | D38: 17.99 | I38: 0.244 | J38: 0.122 | O38: s/ dto | P38: 0.06 | Q38: 12m | R38: S | S38: S | T38: S | U38: 0.10819178 | V38: 0.049287671
B39: 2.0TD_3 Plan Recarga Inteligente | C39: 39.49 | D39: 17.99 | I39: 0.149999 | O39: s/ dto | P39: 0.06 | Q39: 12m | R39: S | S39: S | T39: S | U39: 0.10819178 | V39: 0.049287671
B40: 2.0TD_3 Impulsa 24h | C40: 42.49 | D40: 16.99 | I40: 0.1732 | O40: 20% s/Te (+5% si PIH / PEH+ / UUEEn/ Pack Bienestar) | P40: 0.06 | Q40: 12m | R40: S | S40: N | T40: S | U40: 0.11641096 | V40: 0.046547945
B41: 2.0TD_3 Plan OMIE | C41: 26.93055 | D41: 0.697588 | I41: 0.03 | O41: s/ dto | P41: PVPC | Q41: 12m | R41: N | S41: N | T41: S | U41: 0.073782329 | V41: 0.0019112
B42: 2.0TD_3 Plan OMIE Comunidades | C42: 26.93055 | D42: 0.697588 | I42: 0.03 | O42: s/ dto | P42: PVPC | Q42: 12m | R42: N | S42: N | T42: S | U42: 0.073782329 | V42: 0.0019112
B43: 2.0TD Eventual/Temporal (s/IE) | C43: 60.49 | D43: 2.48 | I43: 0.2881 | J43: 0.2548 | K43: 0.2445 | O43: s/ dto | P43: 0.06 | Q43: 12m | R43: N | S43: N | T43: S | U43: 0.16572603 | V43: 0.0067945205
B45: ELECTRICIDAD - 3.0TD [P > 15kW] Baja Tensión
B46: 3.0TD Impulsa 24h | C46: 21.597514 | D46: 11.670515 | E46: 6.9523 | F46: 5.398084 | G46: 3.258986 | H46: 2.757407 | I46: 0.184 | O46: 20% s/Te (+5% si UUEEn) | P46: 0.03 | Q46: 12m | R46: S | S46: N | T46: S
B47: 3.0TD Impulsa 24h+ | C47: 21.597514 | D47: 11.670515 | E47: 6.9523 | F47: 5.398084 | G47: 3.258986 | H47: 2.757407 | I47: 0.191 | O47: 20% s/Te 1º año y 30% s/Te 2º año (+5% si UUEEn) | P47: 0.03 | Q47: 24m | R47: S | S47: N | T47: S
B48: 3.0TD Impulsa Zero+ | C48: 21.597514 | D48: 14.670515 | E48: 10.9523 | F48: 10.398084 | G48: 9.258986 | H48: 8.757407 | I48: 0.168 | O48: 20% s/Te 1º año y 10% s/Te 2º año (+5% si UUEEn) | P48: 0.03 | Q48: 24m | R48: S | S48: N | T48: S
B49: 3.0TD Impulsa Negocio | C49: 21.597514 | D49: 11.670515 | E49: 6.9523 | F49: 5.398084 | G49: 3.258986 | H49: 2.757407 | I49: 0.269 | J49: 0.166 | O49: 20% s/Te (+5% si UUEEn) | P49: 0.03 | Q49: 12m | R49: S | S49: N | T49: S
B50: 3.0TD Impulsa Valle | C50: 21.597514 | D50: 11.670515 | E50: 6.9523 | F50: 5.398084 | G50: 3.258986 | H50: 2.757407 | I50: 0.269 | J50: 0.135 | O50: 20% s/Te (+5% si UUEEn) | P50: 0.03 | Q50: 12m | R50: S | S50: N | T50: S
B51: 3.0TD Impulsa Estable | C51: 8.75 | D51: 8.75 | E51: 8.75 | F51: 8.75 | G51: 8.75 | H51: 8.75 | I51: 0.199 | O51: 20% s/Te y TP (+5% TE si UUEEn) | P51: 0.03 | Q51: 12m | R51: S | S51: N | T51: S
B52: 3.0TD Comunidad Exclusivo | C52: 24.491635 | D52: 12.696152 | E52: 9.504408 | F52: 7.034486 | G52: 5.370416 | H52: 3.989853 | I52: 0.199 | O52: 20% s/Te (+5% si ACP) + 5% s/te 2año | P52: 0.03 | Q52: 24m | R52: S | S52: N | T52: S
B53: 3.0TD Comunidad Impulsa | C53: 21.597514 | D53: 11.670515 | E53: 6.9523 | F53: 5.398084 | G53: 3.258986 | H53: 2.757407 | I53: 0.179 | O53: 20% s/Te (+5% si ACP) + 5% s/te 2año | P53: 0.03 | Q53: 24m | R53: S | S53: N | T53: S
B54: 3.0TD Comunidad Optima | C54: 21.597514 | D54: 11.670515 | E54: 6.9523 | F54: 5.398084 | G54: 3.258986 | H54: 2.757407 | I54: 0.174 | O54: 20% s/Te (+5% si ACP) + 5% s/te 2año | P54: 0.03 | Q54: 24m | R54: S | S54: N | T54: S
B55: 3.0TD Plan Vehículo Eléctrico | C55: 22.702864 | D55: 12.072887 | E55: 7.859619 | F55: 5.783646 | G55: 3.465543 | H55: 2.419893 | I55: 0.296 | J55: 0.03 | O55: s/ dto | P55: 0.03 | Q55: 12m | R55: S | S55: S | T55: S
B56: 3.0TD Plan Regantes | C56: 22.702864 | D56: 12.072887 | E56: 7.859619 | F56: 5.783646 | G56: 3.465543 | H56: 2.419893 | I56: 0.271 | J56: 0.086 | O56: s/ dto | P56: 0.03 | Q56: 12m | R56: N | S56: N | T56: S
B57: 3.0TD Plan Exclusivo 15%TE | C57: 24.491635 | D57: 12.696152 | E57: 9.504408 | F57: 7.034486 | G57: 5.370416 | H57: 3.989853 | I57: 0.284832 | J57: 0.255068 | K57: 0.227022 | L57: 0.210872 | M57: 0.173647 | N57: 0.185486 | O57: 15% s/Te | P57: 0.05 | Q57: 12m | R57: N | S57: N | T57: S
B58: 3.0TD Plan Exclusivo 26/30%TE | C58: 22.702864 | D58: 12.072887 | E58: 7.859619 | F58: 5.783646 | G58: 3.465543 | H58: 2.419893 | I58: 0.27836 | J58: 0.246127 | K58: 0.214945 | L58: 0.187645 | M58: 0.16539 | N58: 0.174208 | O58: 26% ó 30% s/Te | P58: 0.03 | Q58: 12m | R58: N | S58: N | T58: S
B59: 3.0TD Empresas 10%TE | C59: 20.386009 | D59: 10.622166 | E59: 4.484836 | F59: 3.889635 | G59: 2.517153 | H59: 1.443801 | I59: 0.226429 | J59: 0.188555 | K59: 0.160055 | L59: 0.139455 | M59: 0.124439 | N59: 0.130585 | O59: 10% s/Te | P59: 0.01 | Q59: 12m | R59: N | S59: N | T59: S
B60: 3.0TD Empresa Plus | C60: 20.386009 | D60: 10.622166 | E60: 4.484836 | F60: 3.889635 | G60: 2.517153 | H60: 1.443801 | I60: 0.211765 | J60: 0.178043 | K60: 0.15556 | L60: 0.135386 | M60: 0.120214 | N60: 0.127741 | O60: dto 0,02€/Kwh si consumo >40MWh/a | P60: 0.01 | Q60: 12m | R60: N | S60: N | T60: S
B61: 3.0TD Plan Especial 15%TE | C61: 20.386009 | D61: 10.622166 | E61: 4.484836 | F61: 3.889635 | G61: 2.517153 | H61: 1.443801 | I61: 0.229475 | J61: 0.187326 | K61: 0.159781 | L61: 0.138408 | M61: 0.11993 | N61: 0.128847 | O61: 15% s/Te | P61: 0.01 | Q61: 12m | R61: N | S61: N | T61: S
B62: 3.0TD Plan Verde 15%TE | C62: 22.715388 | D62: 14.625064 | E62: 9.877717 | F62: 7.685923 | G62: 5.403549 | H62: 3.983163 | I62: 0.2268352 | J62: 0.1906194 | K62: 0.1651216 | L62: 0.13839905 | M62: 0.12649885 | N62: 0.144486 | O62: 15% s/Te | P62: 0.03 | Q62: 12m | R62: N | S62: S | T62: S
B63: 3.0TD Plan OMIE 0 | C63: 20.386009 | D63: 10.622166 | E63: 4.484836 | F63: 3.889635 | G63: 2.517153 | H63: 1.443801 | I63: 0.032 | O63: s/ dto | P63: PVPC | Q63: 12m | R63: N | S63: N | T63: S
B64: 3.0TD Plan OMIE 1 | C64: 20.386009 | D64: 10.622166 | E64: 4.484836 | F64: 3.889635 | G64: 2.517153 | H64: 1.443801 | I64: 0.026 | O64: s/ dto | P64: PVPC | Q64: 12m | R64: N | S64: N | T64: S
B65: 3.0TD Plan OMIE 2 | C65: 20.386009 | D65: 10.622166 | E65: 4.484836 | F65: 3.889635 | G65: 2.517153 | H65: 1.443801 | I65: 0.02 | O65: s/ dto | P65: PVPC | Q65: 12m | R65: N | S65: N | T65: S
B66: 3.0TD Plan OMIE 3 | C66: 20.386009 | D66: 10.622166 | E66: 4.484836 | F66: 3.889635 | G66: 2.517153 | H66: 1.443801 | I66: 0.01 | O66: s/ dto | P66: PVPC | Q66: 12m | R66: N | S66: N | T66: S
B67: 3.0TD Eventual/Temporal (s/IE) | C67: 37.626714 | D67: 25.563825 | E67: 9.50043 | F67: 8.215574 | G67: 5.275066 | H67: 3.695917 | I67: 0.354832 | J67: 0.325068 | K67: 0.297022 | L67: 0.280872 | M67: 0.243647 | N67: 0.255486 | O67: s/ dto | P67: 0.03 | Q67: 12m | R67: N | S67: N | T67: S
B69: ELECTRICIDAD - 6.XTD Alta Tensión
B70: 6.1TD
B71: 6.1TD Plan Exclusivo 15%TE | C71: 29.604795 | D71: 15.519427 | E71: 6.80531 | F71: 5.397258 | G71: 2.128542 | H71: 1.005753 | I71: 0.208516 | J71: 0.17828 | K71: 0.160093 | L71: 0.14599 | M71: 0.125772 | N71: 0.135158 | O71: 15% s/Te | P71: 0.05 | Q71: 12m | R71: N | S71: N | T71: S
B72: 6.1TD Empresas 10%TE | C72: 29.604795 | D72: 15.519427 | E72: 6.80531 | F72: 5.397258 | G72: 2.128542 | H72: 1.005753 | I72: 0.18563 | J72: 0.160044 | K72: 0.140496 | L72: 0.127006 | M72: 0.110551 | N72: 0.112799 | O72: 10% s/Te | P72: 0.01 | Q72: 12m | R72: N | S72: N | T72: S
B73: 6.1TD Plan Especial 15%TE | C73: 29.604795 | D73: 15.519427 | E73: 6.80531 | F73: 5.397258 | G73: 2.128542 | H73: 1.005753 | I73: 0.196632 | J73: 0.160545 | K73: 0.135931 | L73: 0.121418 | M73: 0.105781 | N73: 0.107045 | O73: 15% s/Te | P73: 0.01 | Q73: 12m | R73: N | S73: N | T73: S
B74: 6.1TD Empresa Plus | C74: 29.604795 | D74: 15.519427 | E74: 6.80531 | F74: 5.397258 | G74: 2.128542 | H74: 1.005753 | I74: 0.173912 | J74: 0.144547 | K74: 0.120947 | L74: 0.111999 | M74: 0.095988 | N74: 0.09974 | O74: dto 0,01€/Kwh si consumo >100MWh/a | P74: 0.01 | Q74: 12m | R74: N | S74: N | T74: S
B75: 6.1TD Plan Verde 15%TE | C75: 30.604795 | D75: 16.519427 | E75: 7.80531 | F75: 6.397258 | G75: 3.128542 | H75: 2.005753 | I75: 0.197438 | J75: 0.165452 | K75: 0.145955 | L75: 0.132499 | M75: 0.114744 | N75: 0.120771 | O75: 15% s/Te | P75: 0.03 | Q75: 12m | R75: S | S75: S | T75: S
B76: 6.1TD Plan Regantes | C76: 29.604795 | D76: 15.519427 | E76: 6.80531 | F76: 5.397258 | G76: 2.128542 | H76: 1.005753 | I76: 0.194442 | J76: 0.17037 | K76: 0.156321 | L76: 0.132311 | M76: 0.120889 | N76: 0.103635 | O76: s/ dto | P76: 0.03 | Q76: 12m | R76: N | S76: N | T76: S
B77: 6.1TD Plan OMIE 0 | C77: 29.604795 | D77: 15.519427 | E77: 6.80531 | F77: 5.397258 | G77: 2.128542 | H77: 1.005753 | I77: 0.01 | O77: s/ dto | P77: PVPC | Q77: 12m | R77: N | S77: N | T77: S
B78: 6.1TD Plan OMIE 2 | C78: 29.604795 | D78: 15.519427 | E78: 6.80531 | F78: 5.397258 | G78: 2.128542 | H78: 1.005753 | I78: 0.005 | O78: s/ dto | P78: PVPC | Q78: 12m | R78: N | S78: N | T78: S
B79: 6.1TD Eventual/Temporal (s/IE) | C79: 55.165569 | D79: 44.099774 | E79: 21.71596 | F79: 16.116043 | G79: 2.305707 | H79: 1.182235 | I79: 0.278516 | J79: 0.24828 | K79: 0.230093 | L79: 0.21599 | M79: 0.195772 | N79: 0.205158 | O79: s/ dto | P79: 0.03 | Q79: 12m | R79: N | S79: N | T79: S
B80: 6.2TD, 6.3TD, 6.4TD
B81: 6.2TD Plan OMIE 1 | C81: 20.109124 | D81: 11.118439 | E81: 3.711126 | F81: 2.730165 | G81: 1.26763 | H81: 0.606304 | I81: 0.01 | O81: s/ dto | P81: PVPC | Q81: 12m | R81: N | S81: N | T81: S
B82: 6.2TD Eventual/Temporal (s/IE) | C82: 38.856974 | D82: 31.639204 | E82: 13.360229 | F82: 11.081414 | G82: 1.414833 | H82: 0.753102 | I82: 0.255078 | J82: 0.245531 | K82: 0.23173 | L82: 0.223431 | M82: 0.218895 | N82: 0.212845 | O82: s/ dto | P82: 0.03 | Q82: 12m | R82: N | S82: N | T82: S
B83: 6.3TD Plan OMIE 1 | C83: 13.057825 | D83: 7.590081 | E83: 3.063676 | F83: 2.333727 | G83: 1.011652 | H83: 0.482133 | I83: 0.01 | O83: s/ dto | P83: PVPC | Q83: 12m | R83: N | S83: N | T83: S
B84: 6.3TD Eventual/Temporal (s/IE) | C84: 27.333013 | D84: 23.285111 | E84: 11.340036 | F84: 6.741939 | G84: 1.235601 | H84: 0.705758 | I84: 0.244109 | J84: 0.236211 | K84: 0.224294 | L84: 0.215843 | M84: 0.212884 | N84: 0.206318 | O84: s/ dto | P84: 0.03 | Q84: 12m | R84: N | S84: N | T84: S
B85: 6.4TD Plan OMIE 1 | C85: 7.907613 | D85: 4.586872 | E85: 1.460793 | F85: 1.159348 | G85: 0.493615 | H85: 0.230872 | I85: 0.01 | O85: s/ dto | P85: PVPC | Q85: 12m | R85: N | S85: N | T85: S
B86: 6.4TD Eventual/Temporal (s/IE) | C86: 24.523198 | D86: 17.702963 | E86: 7.598059 | F86: 5.777422 | G86: 0.678749 | H86: 0.415848 | I86: 0.234034 | J86: 0.228658 | K86: 0.221104 | L86: 0.215688 | M86: 0.211303 | N86: 0.200351 | O86: s/ dto | P86: 0.03 | Q86: 12m | R86: N | S86: N | T86: S
B88: GAS - RL1 a RL6 Baja Presión
B89: RL1 a RL3
B90: RL.1 Exclusivo 10%TF/TV | C90: 6.55 | I90: 0.100587 | O90: 10% Tf/Tv (15% Tf/Tv si PMG) | Q90: 12m | R90: N | S90: - | T90: S
B91: RL.1 Especial 15%TF/TV | C91: 6.55 | I91: 0.100587 | O91: 15% Tf/Tv (20% Tf/Tv si PMG) | Q91: 12m | R91: N | S91: - | T91: S
B92: RL.2 Exclusivo 10%TF/TV | C92: 11.18 | I92: 0.099244 | O92: 10% Tf/Tv (15% Tf/Tv si PMG) | Q92: 12m | R92: N | S92: - | T92: S
B93: RL.2 Especial 15%TF/TV | C93: 11.18 | I93: 0.099244 | O93: 15% Tf/Tv (20% Tf/Tv si PMG) | Q93: 12m | R93: N | S93: - | T93: S
B94: RL.3 Exclusivo 10%TF/TV | C94: 21.53 | I94: 0.098244 | O94: 10% Tf/Tv (15% Tf/Tv si PMG) | Q94: 12m | R94: N | S94: - | T94: S
B95: RL.3 Especial 15%TF/TV | C95: 21.53 | I95: 0.098244 | O95: 15% Tf/Tv (20% Tf/Tv si PMG) | Q95: 12m | R95: N | S95: - | T95: S
B96: RL4 a RL6
B97: RL.4 Indexada | C97: 66.63 | I97: 0.015 | O97: s/ dto | Q97: 12m | R97: N | S97: - | T97: S
B98: RL.5 Indexada | C98: 257.34 | I98: 0.015 | O98: s/ dto | Q98: 12m | R98: N | S98: - | T98: S
B99: RL.6 Indexada | C99: 1142.7 | I99: 0.015 | O99: s/ dto | Q99: 12m | R99: N | S99: - | T99: S
B101: Compensacion de Excedentes | C101: 0.06
B142: RESUMEN ELECTRICIDAD 2.0TD _ 2 P1 <= 10kW

Sheet AXPO
K4: 1P PLUS (Periodo Único)
A7: SUPER (N1) | I7: ESTANDAR (N2) | Q7: EXTRA (N3)
A9: Peninsula | B9: Precio Término de Energía (€/kWh) Precio Término de potencia (€/kWaño) Consumos 0-3.000.000 kWh/año | I9: Peninsula | J9: Precio Término de Energía (€/kWh) Precio Término de potencia (€/kWaño) Consumos 0-3.000.000 kWh/año | Q9: Peninsula | R9: Precio Término de Energía (€/kWh) Precio Término de potencia (€/kWaño) Consumos 0-3.000.000 kWh/año
A10: Tarifa | B10: P1 | C10: P2 | D10: P3 | E10: P4 | F10: P5 | G10: P6 | I10: Tarifa | J10: P1 | K10: P2 | L10: P3 | M10: P4 | N10: P5 | O10: P6 | Q10: Tarifa | R10: P1 | S10: P2 | T10: P3 | U10: P4 | V10: P5 | W10: P6
A11: 2.0TD | B11: 0.143997 | C11: 0.143997 | D11: 0.143997 | I11: 2.0TD | J11: 0.138921 | K11: 0.138921 | L11: 0.138921 | Q11: 2.0TD | R11: 0.133845 | S11: 0.133845 | T11: 0.133845
A12: 3.0TD | B12: 0.123864 | C12: 0.123864 | D12: 0.123864 | E12: 0.123864 | F12: 0.123864 | G12: 0.123864 | I12: 3.0TD | J12: 0.118788 | K12: 0.118788 | L12: 0.118788 | M12: 0.118788 | N12: 0.118788 | O12: 0.118788 | Q12: 3.0TD | R12: 0.113712 | S12: 0.113712 | T12: 0.113712 | U12: 0.113712 | V12: 0.113712 | W12: 0.113712
I15: POTENCIAS
A18: Precio Término de potencia (€/kWaño) Consumos 0-50.000 kWh/año | I18: Precio Término de potencia (€/kWaño) Consumos 0-50.000 kWh/año | Q18: Precio Término de potencia (€/kWaño) Consumos 0-50.000 kWh/año
A19: Tarifa | B19: P1 | C19: P2 | D19: P3 | E19: P4 | F19: P5 | G19: P6 | I19: Tarifa | J19: P1 | K19: P2 | L19: P3 | M19: P4 | N19: P5 | O19: P6 | Q19: Tarifa | R19: P1 | S19: P2 | T19: P3 | U19: P4 | V19: P5 | W19: P6
A20: 2.0TD | B20: 39.704413 | C20: 21.725423 | I20: 2.0TD | J20: 37.704413 | K20: 19.725423 | Q20: 2.0TD | R20: 34.204413 | S20: 19.725423
A21: 3.0TD | B21: 24.876927 | C21: 15.117621 | D21: 8.981534 | E21: 12.386333 | F21: 14.013851 | G21: 14.442287 | I21: 3.0TD | J21: 23.376927 | K21: 13.617621 | L21: 7.581534 | M21: 11.386333 | N21: 13.013851 | O21: 13.442287 | Q21: 3.0TD | R21: 23.376927 | S21: 13.617621 | T21: 7.481534 | U21: 10.386333 | V21: 10.513851 | W21: 9.942287
K26: ESTABLE
A29: SUPER (N1) | I29: ESTANDAR (N2) | Q29: EXTRA (N3)
A31: Peninsula | B31: Precio Término de Energía (€/kWh) Precio Término de potencia (€/kWaño) Consumos 0-3.000.000 kWh/año | I31: Peninsula | J31: Precio Término de Energía (€/kWh) Precio Término de potencia (€/kWaño) Consumos 0-3.000.000 kWh/año | Q31: Peninsula | R31: Precio Término de Energía (€/kWh) Precio Término de potencia (€/kWaño) Consumos 0-3.000.000 kWh/año
A32: Tarifa | B32: P1 | C32: P2 | D32: P3 | E32: P4 | F32: P5 | G32: P6 | I32: Tarifa | J32: P1 | K32: P2 | L32: P3 | M32: P4 | N32: P5 | O32: P6 | Q32: Tarifa | R32: P1 | S32: P2 | T32: P3 | U32: P4 | V32: P5 | W32: P6
A33: 2.0TD | B33: 0.225997 | C33: 0.155052 | D33: 0.128089 | I33: 2.0TD | J33: 0.214179 | K33: 0.143234 | L33: 0.116272 | Q33: 2.0TD | R33: 0.207905 | S33: 0.13696 | T33: 0.109998
A34: 3.0TD | B34: 0.202053 | C34: 0.17247 | D34: 0.140552 | E34: 0.119471 | F34: 0.106175 | G34: 0.124617 | I34: 3.0TD | J34: 0.190236 | K34: 0.160653 | L34: 0.128735 | M34: 0.107653 | N34: 0.094358 | O34: 0.1128 | Q34: 3.0TD | R34: 0.183962 | S34: 0.154378 | T34: 0.122461 | U34: 0.101379 | V34: 0.088084 | W34: 0.106526
A35: 6.1TD | B35: 0.174387 | C35: 0.15142 | D35: 0.127164 | E35: 0.111237 | F35: 0.100046 | G35: 0.121011 | I35: 6.1TD | J35: 0.162569 | K35: 0.139603 | L35: 0.115347 | M35: 0.09942 | N35: 0.088228 | O35: 0.109193 | Q35: 6.1TD | R35: 0.156295 | S35: 0.133329 | T35: 0.109073 | U35: 0.093146 | V35: 0.081954 | W35: 0.102919
A38: Baleares | B38: Precio Término de Energía (€/kWh) Precio Término de potencia (€/kWaño) Consumos 0-3.000.000 kWh/año | I38: Baleares | J38: Precio Término de Energía (€/kWh) Precio Término de potencia (€/kWaño) Consumos 0-3.000.000 kWh/año | Q38: Baleares | R38: Precio Término de Energía (€/kWh) Precio Término de potencia (€/kWaño) Consumos 0-3.000.000 kWh/año
A39: Tarifa | B39: P1 | C39: P2 | D39: P3 | E39: P4 | F39: P5 | G39: P6 | I39: Tarifa | J39: P1 | K39: P2 | L39: P3 | M39: P4 | N39: P5 | O39: P6 | Q39: Tarifa | R39: P1 | S39: P2 | T39: P3 | U39: P4 | V39: P5 | W39: P6
A40: 2.0TD | B40: 0.228487 | C40: 0.154317 | D40: 0.124392 | I40: 2.0TD | J40: 0.21667 | K40: 0.1425 | L40: 0.112575 | Q40: 2.0TD | R40: 0.210396 | S40: 0.136226 | T40: 0.106301
A41: 3.0TD | B41: 0.177014 | C41: 0.161456 | D41: 0.150842 | E41: 0.138032 | F41: 0.125921 | G41: 0.125213 | I41: 3.0TD | J41: 0.165197 | K41: 0.149638 | L41: 0.139025 | M41: 0.126215 | N41: 0.114104 | O41: 0.113396 | Q41: 3.0TD | R41: 0.158923 | S41: 0.143364 | T41: 0.132751 | U41: 0.119941 | V41: 0.10783 | W41: 0.107122
A42: 6.1TD | B42: 0.151157 | C42: 0.140142 | D42: 0.136471 | E42: 0.126723 | F42: 0.115808 | G42: 0.115573 | I42: 6.1TD | J42: 0.13934 | K42: 0.128325 | L42: 0.124654 | M42: 0.114906 | N42: 0.103991 | O42: 0.103755 | Q42: 6.1TD | R42: 0.133065 | S42: 0.122051 | T42: 0.11838 | U42: 0.108632 | V42: 0.097717 | W42: 0.097481
A45: Canarias | B45: Precio Término de Energía (€/kWh) Precio Término de potencia (€/kWaño) Consumos 0-3.000.000 kWh/año | I45: Canarias | J45: Precio Término de Energía (€/kWh) Precio Término de potencia (€/kWaño) Consumos 0-3.000.000 kWh/año | Q45: Canarias | R45: Precio Término de Energía (€/kWh) Precio Término de potencia (€/kWaño) Consumos 0-3.000.000 kWh/año
A46: Tarifa | B46: P1 | C46: P2 | D46: P3 | E46: P4 | F46: P5 | G46: P6 | I46: Tarifa | J46: P1 | K46: P2 | L46: P3 | M46: P4 | N46: P5 | O46: P6 | Q46: Tarifa | R46: P1 | S46: P2 | T46: P3 | U46: P4 | V46: P5 | W46: P6
A47: 2.0TD | B47: 0.228487 | C47: 0.154317 | D47: 0.124392 | I47: 2.0TD | J47: 0.21667 | K47: 0.1425 | L47: 0.112575 | Q47: 2.0TD | R47: 0.210396 | S47: 0.136226 | T47: 0.106301
A48: 3.0TD | B48: 0.18581 | C48: 0.174827 | D48: 0.158637 | E48: 0.117853 | F48: 0.104941 | G48: 0.125213 | I48: 3.0TD | J48: 0.173993 | K48: 0.16301 | L48: 0.14682 | M48: 0.106036 | N48: 0.093123 | O48: 0.113396 | Q48: 3.0TD | R48: 0.167719 | S48: 0.156736 | T48: 0.140546 | U48: 0.099762 | V48: 0.086849 | W48: 0.107122
A49: 6.1TD | B49: 0.159091 | C49: 0.152228 | D49: 0.143661 | E49: 0.108212 | F49: 0.096658 | G49: 0.115573 | I49: 6.1TD | J49: 0.147274 | K49: 0.140411 | L49: 0.131843 | M49: 0.096394 | N49: 0.08484 | O49: 0.103755 | Q49: 6.1TD | R49: 0.141 | S49: 0.134137 | T49: 0.125569 | U49: 0.09012 | V49: 0.078566 | W49: 0.097481
I52: POTENCIAS
A54: Peninsula | I54: Peninsula | Q54: Peninsula
A55: Precio Término de potencia (€/kWaño) Consumos 0-3.000.000 kWh/año | I55: Precio Término de potencia (€/kWdía) Consumos 0-3.000.000 kWh/año | Q55: Precio Término de potencia (€/kWmes) Consumos 0-3.000.000 kWh/año
A56: Tarifa | B56: P1 | C56: P2 | D56: P3 | E56: P4 | F56: P5 | G56: P6 | I56: Tarifa | J56: P1 | K56: P2 | L56: P3 | M56: P4 | N56: P5 | O56: P6 | Q56: Tarifa | R56: P1 | S56: P2 | T56: P3 | U56: P4 | V56: P5 | W56: P6
A57: 2.0TD | B57: 27.704413 | C57: 0.725423 | I57: 2.0TD | J57: =B57/365 -> 0.075902501 | K57: =C57/365 -> 0.0019874603 | Q57: 2.0TD | R57: =B57/12 -> 2.3087011 | S57: =C57/12 -> 0.060451917
A58: 3.0TD | B58: 20.376927 | C58: 10.617621 | D58: 4.481534 | E58: 3.886333 | F58: 2.513851 | G58: 1.442287 | I58: 3.0TD | J58: =B58/365 -> 0.055827197 | K58: =C58/365 -> 0.029089373 | L58: =D58/365 -> 0.012278175 | M58: =E58/365 -> 0.010647488 | N58: =F58/365 -> 0.006887263 | O58: =G58/365 -> 0.0039514712 | Q58: 3.0TD | R58: =B58/12 -> 1.6980772 | S58: =C58/12 -> 0.88480175 | T58: =D58/12 -> 0.37346117 | U58: =E58/12 -> 0.32386108 | V58: =F58/12 -> 0.20948758 | W58: =G58/12 -> 0.12019058
A59: 6.1TD | B59: 29.595368 | C59: 15.514709 | D59: 6.801881 | E59: 5.393829 | F59: 2.125113 | G59: 1.004181 | I59: 6.1TD | J59: =B59/365 -> 0.0810832 | K59: =C59/365 -> 0.042506052 | L59: =D59/365 -> 0.01863529 | M59: =E59/365 -> 0.014777614 | N59: =F59/365 -> 0.0058222274 | O59: =G59/365 -> 0.0027511808 | Q59: 6.1TD | R59: =B59/12 -> 2.4662807 | S59: =C59/12 -> 1.2928924 | T59: =D59/12 -> 0.56682342 | U59: =E59/12 -> 0.44948575 | V59: =F59/12 -> 0.17709275 | W59: =G59/12 -> 0.08368175
A61: Baleares | I61: Baleares | Q61: Baleares
A62: Precio Término de potencia (€/kWaño) Consumos 0-3.000.000 kWh/año | I62: Precio Término de potencia (€/kWdía) Consumos 0-3.000.000 kWh/año | Q62: Precio Término de potencia (€/kWmes) Consumos 0-3.000.000 kWh/año
A63: Tarifa | B63: P1 | C63: P2 | D63: P3 | E63: P4 | F63: P5 | G63: P6 | I63: Tarifa | J63: P1 | K63: P2 | L63: P3 | M63: P4 | N63: P5 | O63: P6 | Q63: Tarifa | R63: P1 | S63: P2 | T63: P3 | U63: P4 | V63: P5 | W63: P6
A64: 2.0TD | B64: 27.704413 | C64: 0.725423 | I64: 2.0TD | J64: =B64/365 -> 0.075902501 | K64: =C64/365 -> 0.0019874603 | Q64: 2.0TD | R64: =B64/12 -> 2.3087011 | S64: =C64/12 -> 0.060451917
A65: 3.0TD | B65: 20.376927 | C65: 10.617621 | D65: 4.481534 | E65: 3.886333 | F65: 2.513851 | G65: 1.442287 | I65: 3.0TD | J65: =B65/365 -> 0.055827197 | K65: =C65/365 -> 0.029089373 | L65: =D65/365 -> 0.012278175 | M65: =E65/365 -> 0.010647488 | N65: =F65/365 -> 0.006887263 | O65: =G65/365 -> 0.0039514712 | Q65: 3.0TD | R65: =B65/12 -> 1.6980772 | S65: =C65/12 -> 0.88480175 | T65: =D65/12 -> 0.37346117 | U65: =E65/12 -> 0.32386108 | V65: =F65/12 -> 0.20948758 | W65: =G65/12 -> 0.12019058
A66: 6.1TD | B66: 29.595368 | C66: 15.514709 | D66: 6.801881 | E66: 5.393829 | F66: 2.125113 | G66: 1.004181 | I66: 6.1TD | J66: =B66/365 -> 0.0810832 | K66: =C66/365 -> 0.042506052 | L66: =D66/365 -> 0.01863529 | M66: =E66/365 -> 0.014777614 | N66: =F66/365 -> 0.0058222274 | O66: =G66/365 -> 0.0027511808 | Q66: 6.1TD | R66: =B66/12 -> 2.4662807 | S66: =C66/12 -> 1.2928924 | T66: =D66/12 -> 0.56682342 | U66: =E66/12 -> 0.44948575 | V66: =F66/12 -> 0.17709275 | W66: =G66/12 -> 0.08368175
A68: Canarias | I68: Canarias | Q68: Canarias
A69: Precio Término de potencia (€/kWaño) Consumos 0-3.000.000 kWh/año | I69: Precio Término de potencia (€/kWdía) Consumos 0-3.000.000 kWh/año | Q69: Precio Término de potencia (€/kWmes) Consumos 0-3.000.000 kWh/año
A70: Tarifa | B70: P1 | C70: P2 | D70: P3 | E70: P4 | F70: P5 | G70: P6 | I70: Tarifa | J70: P1 | K70: P2 | L70: P3 | M70: P4 | N70: P5 | O70: P6 | Q70: Tarifa | R70: P1 | S70: P2 | T70: P3 | U70: P4 | V70: P5 | W70: P6
A71: 2.0TD | B71: 27.704413 | C71: 0.725423 | I71: 2.0TD | J71: =B71/365 -> 0.075902501 | K71: =C71/365 -> 0.0019874603 | Q71: 2.0TD | R71: =B71/12 -> 2.3087011 | S71: =C71/12 -> 0.060451917
A72: 3.0TD | B72: 20.376927 | C72: 10.617621 | D72: 4.481534 | E72: 3.886333 | F72: 2.513851 | G72: 1.442287 | I72: 3.0TD | J72: =B72/365 -> 0.055827197 | K72: =C72/365 -> 0.029089373 | L72: =D72/365 -> 0.012278175 | M72: =E72/365 -> 0.010647488 | N72: =F72/365 -> 0.006887263 | O72: =G72/365 -> 0.0039514712 | Q72: 3.0TD | R72: =B72/12 -> 1.6980772 | S72: =C72/12 -> 0.88480175 | T72: =D72/12 -> 0.37346117 | U72: =E72/12 -> 0.32386108 | V72: =F72/12 -> 0.20948758 | W72: =G72/12 -> 0.12019058
A73: 6.1TD | B73: 29.595368 | C73: 15.514709 | D73: 6.801881 | E73: 5.393829 | F73: 2.125113 | G73: 1.004181 | I73: 6.1TD | J73: =B73/365 -> 0.0810832 | K73: =C73/365 -> 0.042506052 | L73: =D73/365 -> 0.01863529 | M73: =E73/365 -> 0.014777614 | N73: =F73/365 -> 0.0058222274 | O73: =G73/365 -> 0.0027511808 | Q73: 6.1TD | R73: =B73/12 -> 2.4662807 | S73: =C73/12 -> 1.2928924 | T73: =D73/12 -> 0.56682342 | U73: =E73/12 -> 0.44948575 | V73: =F73/12 -> 0.17709275 | W73: =G73/12 -> 0.08368175
K78: ESTABLE PLUS
A81: SUPER (N1) | I81: ESTANDAR (N2) | Q81: EXTRA (N3)
A83: Peninsula | B83: Precio Término de Energía (€/kWh) Precio Término de potencia (€/kWaño) Consumos 0-3.000.000 kWh/año | I83: Peninsula | J83: Precio Término de Energía (€/kWh) Precio Término de potencia (€/kWaño) Consumos 0-3.000.000 kWh/año | Q83: Peninsula | R83: Precio Término de Energía (€/kWh) Precio Término de potencia (€/kWaño) Consumos 0-3.000.000 kWh/año
A84: Tarifa | B84: P1 | C84: P2 | D84: P3 | E84: P4 | F84: P5 | G84: P6 | I84: Tarifa | J84: P1 | K84: P2 | L84: P3 | M84: P4 | N84: P5 | O84: P6 | Q84: Tarifa | R84: P1 | S84: P2 | T84: P3 | U84: P4 | V84: P5 | W84: P6
A85: 2.0TD | B85: 0.21487 | C85: 0.143925 | D85: 0.116962 | I85: 2.0TD | J85: 0.209611 | K85: 0.138666 | L85: 0.111704 | Q85: 2.0TD | R85: 0.205002 | S85: 0.134057 | T85: 0.107094
A86: 3.0TD | B86: 0.191485 | C86: 0.161901 | D86: 0.129984 | E86: 0.108902 | F86: 0.095606 | G86: 0.114049 | I86: 3.0TD | J86: 0.18647 | K86: 0.156886 | L86: 0.124969 | M86: 0.103887 | N86: 0.090591 | O86: 0.109034 | Q86: 3.0TD | R86: 0.182256 | S86: 0.152673 | T86: 0.120755 | U86: 0.099674 | V86: 0.086378 | W86: 0.10482
A87: 6.1TD | B87: 0.162711 | C87: 0.139745 | D87: 0.115489 | E87: 0.099562 | F87: 0.088371 | G87: 0.109335 | I87: 6.1TD | J87: 0.158651 | K87: 0.135684 | L87: 0.111428 | M87: 0.095501 | N87: 0.08431 | O87: 0.105275 | Q87: 6.1TD | R87: 0.154468 | S87: 0.131502 | T87: 0.107246 | U87: 0.091318 | V87: 0.080127 | W87: 0.101092
A90: Baleares | B90: Precio Término de Energía (€/kWh) Precio Término de potencia (€/kWaño) Consumos 0-3.000.000 kWh/año | I90: Baleares | J90: Precio Término de Energía (€/kWh) Precio Término de potencia (€/kWaño) Consumos 0-3.000.000 kWh/año | Q90: Baleares | R90: Precio Término de Energía (€/kWh) Precio Término de potencia (€/kWaño) Consumos 0-3.000.000 kWh/año
A91: Tarifa | B91: P1 | C91: P2 | D91: P3 | E91: P4 | F91: P5 | G91: P6 | I91: Tarifa | J91: P1 | K91: P2 | L91: P3 | M91: P4 | N91: P5 | O91: P6 | Q91: Tarifa | R91: P1 | S91: P2 | T91: P3 | U91: P4 | V91: P5 | W91: P6
A92: 2.0TD | B92: 0.21736 | C92: 0.14319 | D92: 0.113265 | I92: 2.0TD | J92: 0.212101 | K92: 0.137931 | L92: 0.108006 | Q92: 2.0TD | R92: 0.207492 | S92: 0.133322 | T92: 0.103397
A93: 3.0TD | B93: 0.166446 | C93: 0.150887 | D93: 0.140274 | E93: 0.127464 | F93: 0.115353 | G93: 0.114644 | I93: 3.0TD | J93: 0.16143 | K93: 0.145872 | L93: 0.135258 | M93: 0.122448 | N93: 0.110337 | O93: 0.109629 | Q93: 3.0TD | R93: 0.157217 | S93: 0.141659 | T93: 0.131045 | U93: 0.118235 | V93: 0.106124 | W93: 0.105416
A94: 6.1TD | B94: 0.139482 | C94: 0.128467 | D94: 0.124796 | E94: 0.115048 | F94: 0.104133 | G94: 0.103897 | I94: 6.1TD | J94: 0.135421 | K94: 0.124406 | L94: 0.120735 | M94: 0.110987 | N94: 0.100072 | O94: 0.099837 | Q94: 6.1TD | R94: 0.131238 | S94: 0.120223 | T94: 0.116552 | U94: 0.106804 | V94: 0.09589 | W94: 0.095654
A97: Canarias | B97: Precio Término de Energía (€/kWh) Precio Término de potencia (€/kWaño) Consumos 0-3.000.000 kWh/año | I97: Canarias | J97: Precio Término de Energía (€/kWh) Precio Término de potencia (€/kWaño) Consumos 0-3.000.000 kWh/año | Q97: Canarias | R97: Precio Término de Energía (€/kWh) Precio Término de potencia (€/kWaño) Consumos 0-3.000.000 kWh/año
A98: Tarifa | B98: P1 | C98: P2 | D98: P3 | E98: P4 | F98: P5 | G98: P6 | I98: Tarifa | J98: P1 | K98: P2 | L98: P3 | M98: P4 | N98: P5 | O98: P6 | Q98: Tarifa | R98: P1 | S98: P2 | T98: P3 | U98: P4 | V98: P5 | W98: P6
A99: 2.0TD | B99: 0.21736 | C99: 0.14319 | D99: 0.113265 | I99: 2.0TD | J99: 0.212101 | K99: 0.137931 | L99: 0.108006 | Q99: 2.0TD | R99: 0.207492 | S99: 0.133322 | T99: 0.103397
A100: 3.0TD | B100: 0.175242 | C100: 0.164259 | D100: 0.148069 | E100: 0.107285 | F100: 0.094372 | G100: 0.114644 | I100: 3.0TD | J100: 0.170227 | K100: 0.159244 | L100: 0.143053 | M100: 0.102269 | N100: 0.089357 | O100: 0.109629 | Q100: 3.0TD | R100: 0.166013 | S100: 0.15503 | T100: 0.13884 | U100: 0.098056 | V100: 0.085144 | W100: 0.105416
A101: 6.1TD | B101: 0.147416 | C101: 0.140553 | D101: 0.131986 | E101: 0.096537 | F101: 0.084983 | G101: 0.103897 | I101: 6.1TD | J101: 0.143355 | K101: 0.136492 | L101: 0.127925 | M101: 0.092476 | N101: 0.080922 | O101: 0.099837 | Q101: 6.1TD | R101: 0.139173 | S101: 0.13231 | T101: 0.123742 | U101: 0.088293 | V101: 0.076739 | W101: 0.095654
I104: POTENCIAS
A106: Peninsula | I106: Peninsula | Q106: Peninsula
A107: Precio Término de potencia (€/kWaño) Consumos 0-3.000.000 kWh/año | I107: Precio Término de potencia (€/kWaño) Consumos 0-3.000.000 kWh/año | Q107: Precio Término de potencia (€/kWaño) Consumos 0-3.000.000 kWh/año
A108: Tarifa | B108: P1 | C108: P2 | D108: P3 | E108: P4 | F108: P5 | G108: P6 | I108: Tarifa | J108: P1 | K108: P2 | L108: P3 | M108: P4 | N108: P5 | O108: P6 | Q108: Tarifa | R108: P1 | S108: P2 | T108: P3 | U108: P4 | V108: P5 | W108: P6
A109: 2.0TD | B109: 35.704413 | C109: 18.725423 | I109: 2.0TD | J109: 33.704413 | K109: 16.725423 | Q109: 2.0TD | R109: 31.704413 | S109: 14.725423
A110: 3.0TD | B110: 23.376927 | C110: 13.617621 | D110: 7.481534 | E110: 10.886333 | F110: 11.513851 | G110: 11.442287 | I110: 3.0TD | J110: 21.876927 | K110: 12.117621 | L110: 5.981534 | M110: 9.386333 | N110: 10.013851 | O110: 9.942287 | Q110: 3.0TD | R110: 20.876927 | S110: 11.117621 | T110: 4.981534 | U110: 7.386333 | V110: 7.513851 | W110: 7.442287
A111: 6.1TD | B111: 32.595368 | C111: 18.514709 | D111: 9.801881 | E111: 12.393829 | F111: 11.125113 | G111: 11.004181 | I111: 6.1TD | J111: 31.095368 | K111: 17.014709 | L111: 8.301881 | M111: 10.893829 | N111: 9.625113 | O111: 9.504181 | Q111: 6.1TD | R111: 30.095368 | S111: 16.014709 | T111: 7.301881 | U111: 8.893829 | V111: 7.125113 | W111: 7.004181
A113: Baleares | I113: Baleares | Q113: Baleares
A114: Precio Término de potencia (€/kWaño) Consumos 0-3.000.000 kWh/año | I114: Precio Término de potencia (€/kWaño) Consumos 0-3.000.000 kWh/año | Q114: Precio Término de potencia (€/kWaño) Consumos 0-3.000.000 kWh/año
A115: Tarifa | B115: P1 | C115: P2 | D115: P3 | E115: P4 | F115: P5 | G115: P6 | I115: Tarifa | J115: P1 | K115: P2 | L115: P3 | M115: P4 | N115: P5 | O115: P6 | Q115: Tarifa | R115: P1 | S115: P2 | T115: P3 | U115: P4 | V115: P5 | W115: P6
A116: 2.0TD | B116: =B109 -> 35.704413 | C116: =C109 -> 18.725423 | I116: 2.0TD | J116: 33.704413 | K116: 16.725423 | Q116: 2.0TD | R116: 31.704413 | S116: 14.725423
A117: 3.0TD | B117: =B110 -> 23.376927 | C117: =C110 -> 13.617621 | D117: =D110 -> 7.481534 | E117: =E110 -> 10.886333 | F117: =F110 -> 11.513851 | G117: =G110 -> 11.442287 | I117: 3.0TD | J117: 21.876927 | K117: 12.117621 | L117: 5.981534 | M117: 9.386333 | N117: 10.013851 | O117: 9.942287 | Q117: 3.0TD | R117: 20.876927 | S117: 11.117621 | T117: 4.981534 | U117: 7.386333 | V117: 7.513851 | W117: 7.442287
A118: 6.1TD | B118: =B111 -> 32.595368 | C118: =C111 -> 18.514709 | D118: =D111 -> 9.801881 | E118: =E111 -> 12.393829 | F118: =F111 -> 11.125113 | G118: =G111 -> 11.004181 | I118: 6.1TD | J118: 31.095368 | K118: 17.014709 | L118: 8.301881 | M118: 10.893829 | N118: 9.625113 | O118: 9.504181 | Q118: 6.1TD | R118: 30.095368 | S118: 16.014709 | T118: 7.301881 | U118: 8.893829 | V118: 7.125113 | W118: 7.004181
A120: Canarias | I120: Canarias | Q120: Canarias
A121: Precio Término de potencia (€/kWaño) Consumos 0-3.000.000 kWh/año | I121: Precio Término de potencia (€/kWaño) Consumos 0-3.000.000 kWh/año | Q121: Precio Término de potencia (€/kWaño) Consumos 0-3.000.000 kWh/año
A122: Tarifa | B122: P1 | C122: P2 | D122: P3 | E122: P4 | F122: P5 | G122: P6 | I122: Tarifa | J122: P1 | K122: P2 | L122: P3 | M122: P4 | N122: P5 | O122: P6 | Q122: Tarifa | R122: P1 | S122: P2 | T122: P3 | U122: P4 | V122: P5 | W122: P6
A123: 2.0TD | B123: =B109 -> 35.704413 | C123: =C109 -> 18.725423 | I123: 2.0TD | J123: 33.704413 | K123: 16.725423 | Q123: 2.0TD | R123: 31.704413 | S123: 14.725423
A124: 3.0TD | B124: =B110 -> 23.376927 | C124: =C110 -> 13.617621 | D124: =D110 -> 7.481534 | E124: =E110 -> 10.886333 | F124: =F110 -> 11.513851 | G124: =G110 -> 11.442287 | I124: 3.0TD | J124: 21.876927 | K124: 12.117621 | L124: 5.981534 | M124: 9.386333 | N124: 10.013851 | O124: 9.942287 | Q124: 3.0TD | R124: 20.876927 | S124: 11.117621 | T124: 4.981534 | U124: 7.386333 | V124: 7.513851 | W124: 7.442287
A125: 6.1TD | B125: =B111 -> 32.595368 | C125: =C111 -> 18.514709 | D125: =D111 -> 9.801881 | E125: =E111 -> 12.393829 | F125: =F111 -> 11.125113 | G125: =G111 -> 11.004181 | I125: 6.1TD | J125: 31.095368 | K125: 17.014709 | L125: 8.301881 | M125: 10.893829 | N125: 9.625113 | O125: 9.504181 | Q125: 6.1TD | R125: 30.095368 | S125: 16.014709 | T125: 7.301881 | U125: 8.893829 | V125: 7.125113 | W125: 7.004181
